Workbook

Sheet Laptop Replacement 2020
A1: SEB2020L | B1: 2020 | C1: 5CG014DTP7 | E1: HP Elitebook 840 G6 | F1: AC | G1: Andrew Chin | H1: ICT | I1: 17/11/2020 | J1: 17/11/2020 | K1: Replace NB | L1: Reallocate to CFS
A2: SEB2020L | B2: 0818 | C2: 5CG014DRQ2 | E2: HP Elitebook 840 G6 | F2: MFS | G2: Amalina Hilmy | H2: Credit Control | I2: 25/01/2021 | J2: 25/01/2021
A3: SEB2020L | B3: 0817 | C3: 5CG014DRPB | E3: HP Elitebook 840 G6 | F3: Art | G3: Irina Binti Azman Durai | H3: ICT | I3: 44442 | J3: 44472 | K3: Replacement
A4: SEB2020L | B4: 0816 | C4: 5CG014DTPP | E4: HP Elitebook 840 G6 | F4: AC | G4: Chong Hui Ching | H4: PD | I4: 44200 | J4: 44200 | K4: New joiner
A5: SEB2020L | B5: 0815 | C5: 5CG014DQCS | E5: HP Elitebook 840 G6 | F5: AC | G5: Junetta Manggie | H5: HR | I5: 44199 | J5: 44230 | K5: New
A6: SEB2020L | B6: 0814 | C6: 5CG014DRPV | E6: HP Elitebook 840 G6 | F6: Adam | G6: Tan Ming Wei | H6: Project Delivery | I6: 44230 | J6: 44258 | K6: New
A7: SEB2020L | B7: 0813 | C7: 5CG014DTQ7 | E7: HP Elitebook 840 G6 | F7: Art | G7: Alvin Lim Khiok Leong | H7: SER COO | I7: 23/02/2021 | J7: 44230 | K7: Temporary use | L7: Now permanent for Chai Tze Kong
A8: SEB2020L | B8: 0812 | C8: 5CG014DSMD | E8: HP Elitebook 840 G6 | F8: Adam | G8: Collin Tiong Inn Seng | H8: Distribution | I8: 22/2/2021 | J8: 44289 | K8: Replacement | L8: Replace HP 440 G2
A9: SEB2020L | B9: 0811 | C9: 5CG014DSY9 | E9: HP Elitebook 840 G6 | F9: Art | G9: William Ho Ming Chung | H9: PD | I9: 22/02/2021 | J9: 44289
A10: SEB2020L | B10: 0810 | C10: 5CG014DQNM | E10: HP Elitebook 840 G6 | F10: Adam | G10: Nur Azmina Binti Zainuddin | H10: Strategy & Corporate | I10: 13/2/2021 | J10: 44289 | K10: New
A11: SEB2020L | B11: 0809 | C11: 5CG014DRPG | E11: HP Elitebook 840 G6 | F11: Art | G11: Mohammed Faiz Julaihi | H11: Contract & Procurement | I11: 44471 | J11: 44289
A12: SEB2020L | B12: 0808 | C12: HCKDYX2 | E12: Dell Latitude 7424 | F12: JW | G12: Aniq | I12: 44230 | J12: 44230 | K12: Temporary swap
A13: SEB2020L | B13: 0807 | C13: 5GD045GBSH | E13: HP ZBook 15 G6 | F13: Adam | G13: Sharika A/P Kaliani | H13: Coal | I13: 44532 | J13: 18/2/2021 | K13: Replace Desktop | L13: Workstation with Workstation
A14: SEB2020L | B14: 0806 | C14: 5CG91673MC | E14: HP Elitebook 840 G6 | F14: MFS | G14: Jeffery Lai | H14: Wisma Sesco | I14: 44228 | K14: New Joiner
A15: SEB2020L | B15: 0805 | C15: 5CG014DT75 | E15: HP Elitebook 840 G6 | F15: Vendor | G15: Dygku Mimi Rosfarlina | H15: Sibu | I15: 44228 | J15: 44471 | K15: New Joiner
A16: SEB2020L | B16: 0804 | C16: 5CG014DT7X | E16: HP Elitebook 840 G6 | F16: YIP | G16: Davina Anak Eli | H16: SESCO Operational Excellence | I16: 29/01/2021 | J16: 44257 | K16: Replace Notebook | L16: Dell 3450
A17: SEB2020L | B17: 0803 | C17: 5CG014DQDS | E17: HP Elitebook 840 G6 | F17: Vendor | G17: Wong Chit Sing | H17: Sibu | I17: 29/01/2021 | K17: Replace Desktop PC
A18: SEB2020L | B18: 0802 | C18: 5CG014DTN8 | E18: HP Elitebook 840 G6 | F18: Vendor | G18: Leman Ak Aji | H18: Sibu | I18: 29/01/2021 | K18: Replace Desktop PC
A19: SEB2020L | B19: 0801 | C19: 5CG014DT8P | E19: HP Elitebook 840 G6 | F19: Vendor | G19: Abang Ismail B. Abang Daud | H19: Sibu | I19: 29/01/2021 | K19: Replace Desktop PC | L19: OSSM # S3784
A20: SEB2020L | B20: 0800 | C20: 5CG014DQQ2 | E20: HP Elitebook 840 G6 | F20: JW | G20: Muhammad Hanif | H20: Land & Wayleave | I20: 29/01/2021 | K20: New
A21: SEB2020L | B21: 0799 | C21: 5CG014DTN1 | E21: HP Elitebook 840 G6 | F21: JW | G21: Lee Yew Shien | H21: ICT | I21: 28/01/2021 | J21: 44198 | K21: New Joiner
A22: SEB2020L | B22: 0798 | C22: 5CG014DQF2 | E22: HP Elitebook 840 G6 | F22: AC | G22: Dayang Norsidah Binti Awang Rashid | H22: SEB Power | I22: 27/01/2021 | J22: 29/01/2021 | K22: Replace Noteobok | L22: Replacement on Stolen Unit sn: 5CG014DQDF
A23: SEB2020L | B23: 0797 | C23: 5CG0207MMX | E23: HP Elitebook 840 G6 | F23: Art | G23: Shazril Azizie Bin Zaidi | H23: Transmission | I23: 28/01/2021 | J23: 44471 | K23: Replace Desktop
A24: SEB2020L | B24: 0796 | C24: 5CG0207MNS | E24: HP Elitebook 840 G6 | F24: AC | G24: Kho Li Yen | H24: Retail (Sibu) | I24: 22/01/2021 | J24: 25/01/2021 | K24: Replace Desktop
A25: SEB2020L | B25: 0795 | C25: 5CG014DSXN | E25: HP Elitebook 840 G6 | F25: JW | G25: Liong Yiing Yang | H25: Retail (Sibu) | I25: 21/01/2021 | J25: 25/01/2021 | K25: Replace Desktop
A26: SEB2020L | B26: 0794 | C26: 5CG014DSY4 | E26: HP Elitebook 840 G6 | F26: Art | G26: Syamil Bin Ibrahim | H26: Distribution | I26: 21/01/2021 | J26: 25/01/2021
A27: SEB2020L | B27: 0793 | C27: 5CG014DQFF | E27: HP Elitebook 840 G6 | F27: YIP | G27: Hou Mee King | H27: Payment Bintulu | I27: 22/01/2021 | J27: 25/01/2021 | K27: Replace Desktop PC
A28: SEB2020L | B28: 0792 | C28: 5CG01472F6 | E28: HP ZBook 14 U G6 | F28: AC | G28: Kelvin Jee | H28: Strategy & Corporate | I28: 20/01/2021 | J28: 22/01/2021 | K28: Replace Notebook | L28: Replace Lenovo T470
A29: SEB2020L | B29: 0791 | C29: 5CD014DRMV | E29: HP Elitebook 840 G6 | F29: AC | G29: Andrew Lim Kheng Chuan | H29: Project Delivery | I29: 20/01/2021 | J29: 15/2/2021 | K29: New
A30: SEB2020L | B30: 0790 | C30: 5CG014DT7S | E30: HP Elitebook 840 G6 | F30: AC | G30: Simon Fowel Tami | H30: Generation Asset Management | I30: 28/06/2021 | J30: 44390 | K30: Replacement
A31: SEB2020L | B31: 0789 | C31: 5CG014DQDH | E31: HP Elitebook 840 G6 | F31: Adam | G31: lvis | H31: GCEO | I31: 16/1/2021 | J31: 18/01/2021 | K31: Replace Notebook
A32: SEB2020L | B32: 0788 | C32: 5CG014DQG2 | E32: HP Elitebook 840 G6 | F32: Art | G32: Fung Kwong Meng | H32: PD | I32: 14/01/2021 | J32: 15/02/2021
A33: SEB2020L | B33: 0787 | C33: 5CG014DSLZ | E33: HP Elitebook 840 G6 | F33: Adam | G33: Yii Yong Chong | H33: Distribution (Bintulu RO) | I33: 13/1/2021 | K33: New Joiner
A34: SEB2020L | B34: 0786 | C34: 5CG014DQD8 | E34: HP Elitebook 840 G6 | F34: AC | G34: Awang Hasnan Bin Awang Abdul Rahman | H34: IA | I34: 13/01/2021 | J34: 14/01/2021 | K34: Replace Noteobok | L34: Replace HP 440 G2
A35: SEB2020L | B35: 0785 | C35: 5CG014DQ1V | E35: HP Elitebook 840 G6 | F35: Art | G35: Anthony Wong Chiew Wu | H35: Finance | I35: 13/01/2021 | J35: 44198 | K35: New Joiner
A36: SEB2020L | B36: 0784 | C36: 5CG014DSLW | E36: HP Elitebook 840 G6 | F36: Adam | G36: Esther Moa Shu Qi | H36: PD | I36: 44531 | J36: 15/1/2021 | K36: New Joiner
A37: SEB2020L | B37: 0783 | C37: 5CG014DSLJ | E37: HP Elitebook 840 G6 | F37: Adam | G37: Mohamad Ardzuan Bin Aman | H37: Hydro | I37: 44501 | K37: Replace Desktop PC
A38: SEB2020L | B38: 0782 | C38: 5CG014DQ1K | E38: HP Elitebook 840 G6 | F38: Art | G38: Nur Amanina Binti Mohd Hanafi | H38: HSSE | I38: 44531 | J38: 22/03/2021
A39: SEB2020L | B39: 0781 | C39: 5CG014DRN8 | D39: Bitlocker | E39: HP Elitebook 840 G6 | F39: CFJ | G39: Chou Yeng Khai Liong Teck Hua | H39: ICT Operation | I39: 44501 | J39: 15/01/2021 | K39: New Joiner | M39: 5658710E-A0AB-472E-B569-058491D563B4 | N39: 398783-168421-010571-351538-075823-568711-554400-150337
A40: SEB2020L | B40: 0780 | C40: 5CG0207MNX | E40: HP Elitebook 840 G6 | F40: JW | G40: Tan Yong Siang | H40: Maintenance | I40: 44409 | J40: 44218 | K40: Replacement
A41: SEB2020L | B41: 0779 | C41: 5CG0207MP8 | E41: HP Elitebook 840 G6 | F41: Art | G41: Ahmad Syahmi Bin Lawrence | H41: PD | I41: 44409 | J41: 15/1/2021 | K41: New Joiner
A42: SEB2020L | B42: 0778 | C42: 5CG0207MN8 | E42: HP Elitebook 840 G6 | F42: Adam | G42: Melvina Tan | H42: Research & Development | I42: 44348 | J42: 44378 | K42: Replacement | L42: Returned Dell 3470 on 6/1/2021
A43: SEB2020L | B43: 0777 | C43: 5CD0501FRB | E43: HP ZBook 15 G6 | F43: Art | G43: Paul Kan | H43: ICT | I43: 44317 | J43: 44288 | K43: New | L43: For Project
A44: SEB2020L | B44: 0776 | C44: 5CD0501FV4 | E44: HP ZBook 15 G6 | F44: Art | G44: Abg Mohd Fakhri Bin Abg Mohtar | H44: SEB Power | I44: 44348 | J44: 44378 | K44: Replace Notebook | L44: Replace Microsoft Surface PRO
A45: SEB2020L | B45: 0775 | C45: 5CG014DQ1H | E45: HP Elitebook 840 G6 | F45: Art | G45: Litad Ajeng | H45: SEB Power | I45: 20/10/2020 | J45: 27/10/2020 | K45: Replace Desktop PC
A46: SEB2020L | B46: 0770 | C46: 5CG014DSXX | E46: HP Elitebook 840 G6 | G46: Fabian Anak Wilson Jana | K46: In Stock
A47: SEB2020L | B47: 0751 | C47: 5CG0207MNN | E47: HP Elitebook 840 G6 | F47: YIP | G47: Dayang Norhabibah Bt Awang Malek | H47: SIBU | J47: 44471 | K47: Replace Desktop PC
A48: SEB2020L | B48: 0711 | C48: 5CG014DRMW | E48: HP Elitebook 840 G6 | F48: BASB | G48: Muhammad Shafiezal Bin Othman | H48: Distribution (WR) | I48: 30/12/2020 | K48: Replace Desktop PC
A49: SEB2020L | B49: 0710 | C49: 5CD045GBSD | E49: HP ZBook 15 G6 | F49: JW | G49: Chiew Sze Fong | H49: PD | I49: 44195 | J49: 44218 | K49: Replacement | L49: Returned Dell 3470 on 221/2021
A50: SEB2020L | B50: 0709 | C50: 5CG014DT7J | E50: HP Elitebook 840 G6 | F50: JW | G50: Dayang Hamidah | H50: RES | I50: 44187 | J50: 44200 | K50: New | L50: Report duty on 04/01/2021
A51: SEB2020L | B51: 0708 | C51: 5CD045GBSF | E51: HP ZBook 15 G6 | F51: Art | G51: Dennis Anak Lee | H51: Distribution | I51: 44188 | J51: 44409 | K51: Replacement
A52: SEB2020L | B52: 0707 | C52: 5CG014DT6X | E52: HP Elitebook 840 G6 | F52: Adam | G52: Lee May Hui | H52: SESCO | I52: 23/12/2020 | J52: 15/1/2021 | K52: Replace NB
A53: SEB2020L | B53: 0706 | C53: 5CG014DQQ5 | E53: HP Elitebook 840 G6 | F53: CFJ | G53: Mohamad Yakub Bin Junaidi | H53: Distribution (IM) | I53: 22/12/2020 | J53: 22/12/2020 | K53: Replace Desktop PC | L53: Donation HP600. 22/12/2020
A54: SEB2020L | B54: 0705 | C54: 5CG014DQ16 | E54: HP Elitebook 840 G6 | F54: JW | G54: Kon Jia Hui | I54: 44183 | J54: 44200 | K54: New | L54: Report duty on 04/01/2021
A55: SEB2020L | B55: 0704 | C55: 5CG014DQNF | E55: HP Elitebook 840 G6 | F55: Art | G55: Nur Sharmilla Ahmad | H55: Finance | I55: 44186 | J55: 44287 | K55: New
A56: SEB2020L | B56: 0703 | C56: 5CG014DSLS | E56: HP Elitebook 840 G6 | F56: Adam | G56: Andrew Ngisun | H56: HSSE | I56: 18/12/2020 | J56: 24/12/2020 | K56: Replacement
A57: SEB2020L | B57: 0702 | C57: 5CG014DQ2X | E57: HP Elitebook 840 G6 | F57: Adam | G57: Lee Yen Hwa | H57: Finance | I57: 17/12/2020 | J57: 44287 | K57: New | L57: Report duty on 04/01/2021
A58: SEB2020L | B58: 0701 | C58: 5CG014DSXS | E58: HP Elitebook 840 G6 | F58: Art | G58: Nasrulridza Bin Yusuf | H58: Finance | I58: 17/12/2020 | J58: 44200 | K58: New
A59: SEB2020L | B59: 0700 | C59: 5CG014DQQG | E59: HP Elitebook 840 G6 | F59: ATO | G59: Ng Sze Hui | H59: Distribution | I59: in progress | K59: Replace Desktop PC | L59: Ticket(S2625)
A60: SEB2020L | B60: 0699 | C60: 5CG014DQ1W | E60: HP Elitebook 840 G6 | F60: Art | G60: Voon Mei Yen | H60: IA | I60: 15/12/2020 | J60: 44200 | K60: New
A61: SEB2020L | B61: 0698 | C61: 5CG014DSY6 | E61: HP Elitebook 840 G6 | F61: Art | G61: Yong Chee Siang | H61: IA | I61: 44175 | J61: 15//01/2021 | K61: New
A62: SEB2020L | B62: 0697 | C62: 5CG014DT8S | E62: HP Elitebook 840 G6 | F62: AC | G62: Lee Ee Hun | H62: IA | I62: 44086 | J62: 44086 | K62: New
A63: SEB2020L | B63: 0696 | C63: 5CG014DQF4 | E63: HP Elitebook 840 G6 | F63: ATO | G63: Ting Kwong Hieng | H63: HSSE Batang Ai | I63: 44147
A64: SEB2020L | B64: 0695 | C64: 5CG014DQP6 | E64: HP Elitebook 840 G6 | F64: Adam | G64: Florence Lim Siang | H64: Project Delivery | I64: 44086 | J64: 44086 | K64: Replace NB | L64: Returned 3470 on 09/12/2020
A65: SEB2020L | B65: 0694 | C65: 5CG014DQ35 | E65: HP Elitebook 840 G6 | F65: CFJ | G65: Oliver Bernard Anak Mura | H65: Distribution / OPM | I65: 44024 | J65: 44086 | K65: Replace Desktop PC
A66: SEB2020L | B66: 0693 | C66: 5CG014DQ21 | E66: HP Elitebook 840 G6 | F66: Adam | G66: Vijayan Kurup | H66: HSSE | I66: 43933 | J66: 44024 | K66: Replace Desktop PC
A67: SEB2020L | B67: 0692 | C67: 5CG014DRP7 | E67: HP Elitebook 840 G6 | F67: ATO | G67: Alloysius Norbert | H67: Batang Ai PS | I67: 30/11/2020 | K67: Replace Desktop PC | L67: to NB (Ticket S2396)
A68: SEB2020L | B68: 0691 | C68: 5CG014DRNK | E68: HP Elitebook 840 G6 | F68: AC | G68: FABRON CALVIN JULIAN | H68: Grid System Operator | I68: 30/11/2020 | J68: 43873 | K68: New
A69: SEB2020L | B69: 0684 | C69: 5CG014DSKQ | E69: HP Elitebook 840 G6 | F69: Art | G69: Sukinah binti Sayed Hasni | H69: CoSec | I69: 44024 | J69: 44174
A70: SEB2020L | B70: 0683 | C70: 5CG014DQ3Q | E70: HP Elitebook 840 G6 | F70: Adam | G70: Tiong Ling Ing | H70: Distribution (Bintulu RO) | I70: 43902 | K70: Replace NB
A71: SEB2020L | B71: 0682 | C71: 5CG014DT84 | E71: HP Elitebook 840 G6 | F71: Adam | G71: Cheong Chai Yeen | H71: ICT | I71: 43842 | J71: 44024 | K71: Replace NB
A72: SEB2020L | B72: 0681 | C72: 5CG014DRNB | E72: HP Elitebook 840 G6 | F72: Art | G72: Randy Anderson Sibat Anak Joseph Koh | H72: Land & Wayleave | I72: 43842 | J72: 14/12/2020 | K72: New
A73: SEB2020L | B73: 0680 | C73: 5CG014DQNR | E73: HP Elitebook 840 G6 | F73: Adam | G73: Nuur Aina Najiehah Binti Brahim Lumpu | H73: Contract & Procurement | I73: 30/11/2020 | J73: 44024 | K73: New | L73: Report duty on 1/12/2020
A74: SEB2020L | B74: 0679 | C74: 5CG014DRQ7 | E74: HP Elitebook 840 G6 | F74: Art | G74: Lai Lee Hua | H74: Transmission | I74: 44159 | J74: 25/11/2020
A75: SEB2020L | B75: 0678 | C75: 5CG014DQCX | E75: HP Elitebook 840 G6 | F75: Adam | G75: Marianne Runa Chiam | H75: CSR | I75: 23/11/2020 | J75: 43872
A76: SEB2020L | B76: 0677 | C76: 5CG014DQN1 | E76: HP Elitebook 840 G6 | F76: JW | G76: Ting Siaw Yeng | H76: Smart Grid | I76: 44160 | J76: 44200 | K76: New | L76: Report Duty = 04/01/2021
A77: SEB2020L | B77: 0676 | C77: 5CG014DQD9 | E77: HP Elitebook 840 G6 | F77: JW | G77: Khairul Akmal | H77: PD | I77: 44159 | J77: 44166 | K77: New | L77: Report duty on 01/12/2020
A78: SEB2020L | B78: 0675 | C78: 5CG014DTNQ | E78: HP Elitebook 840 G6 | F78: JW | G78: Boniface | H78: LEGAL | I78: 44158 | L78: To Reassign
A79: SEB2020L | B79: 0674 | C79: 5CG014DQDN | E79: HP Elitebook 840 G6 | F79: JW | G79: Mohd Syarifuddin Bin Abdul Rahim | H79: HSSE | I79: 44155 | J79: 24/11/2020 | K79: Replacement | L79: Ex-Anisa Laii of HSSE, resign Jun 2021
A80: SEB2020L | B80: 0673 | C80: 5CG014DTPR | E80: HP Elitebook 840 G6 | F80: Adam | G80: Noor Tasha Binti Husaini | H80: Legal | I80: 20/11/2020 | J80: 23/11/2020 | K80: Replace Desktop PC | L80: Returned Desktop on 1/12/2020
A81: SEB2020L | B81: 0672 | C81: 5CG014DQD1 | E81: HP Elitebook 840 G6 | F81: Adam | G81: Mohamad Rezki Bin Aswan | H81: Group Company Secretary | I81: 19/11/2020 | J81: 23/11/2020 | K81: Replace Desktop PC | L81: Returned Desktop on 1/12/2020
A82: SEB2020L | B82: 0671 | C82: 5CG014DQD0 | E82: HP Elitebook 840 G6 | F82: Adam | G82: Grace Anak Brandah | H82: Project Delivery | I82: 19/11/2020 | J82: 44208 | K82: New Joiner | L82: Report duty on 01/12/2020
A83: SEB2020L | B83: 0670 | C83: 5CG014DQD2 | E83: HP Elitebook 840 G6 | F83: Art | G83: Wong Tien Hee | H83: Transmission | I83: 20/11/2020 | J83: 44055
A84: SEB2020L | B84: 0669 | C84: 5CG014DQ2T | E84: HP Elitebook 840 G6 | F84: Art | G84: Valarea Marianne Hansoo | H84: Legal | I84: 20/11/2020 | J84: 23/11/2020 | K84: Replace Desktop PC | L84: Returned Desktop on 1/12/2020
A85: SEB2020L | B85: 0668 | C85: 5CG014DTPF | E85: HP Elitebook 840 G6 | F85: JW | G85: Peter Igam | H85: Project Delivery | I85: 44153 | J85: 20/11/2020 | K85: Replace NB | L85: Returned on 20/11/2020
A86: SEB2020L | B86: 0667 | C86: 5CG014DTNT | E86: HP Elitebook 840 G6 | F86: Adam | G86: Jonah Lau Horng | H86: Finance | I86: 18/11/2020 | J86: 44287 | K86: New Joiner | L86: Report duty on 04/01/2021
A87: SEB2020L | B87: 0666 | C87: 5CG014DSX6 | E87: HP Elitebook 840 G6 | F87: Adam | G87: Farrely Anak Tapa | H87: BFI | I87: 17/11/2020 | J87: 19/11/2020 | K87: Replace Desktop PC | L87: Returned Desktop on 02/12/2020
A88: SEB2020L | B88: 0665 | C88: 5CG014DT78 | E88: HP Elitebook 840 G6 | F88: Art | G88: Kun Wee Na | H88: Finance | I88: 18/11/2020 | J88: 44166
A89: SEB2020L | B89: 0664 | C89: 5CG014DT71 | E89: HP Elitebook 840 G6 | F89: ATO | G89: Dawi Plin | H89: HSSE | I89: 16/11/2020 | K89: Replacement
A90: SEB2020L | B90: 0663 | C90: 5CG014DRNL | E90: HP Elitebook 840 G6 | F90: Adam | G90: Mohamad Azlan Bin Sakdi | H90: Finance | I90: 16/11/2020 | J90: 43873 | K90: Replacement
A91: SEB2020L | B91: 0662 | C91: 5CG014DQ29 | E91: HP Elitebook 840 G6 | F91: Art | G91: Desmond Ee Pei Lian | H91: PD | I91: 16/11/2020 | J91: 44162
A92: SEB2020L | B92: 0661 | C92: 5CG014DRNG | E92: HP Elitebook 840 G6 | F92: JW | G92: Gabreil Barry | H92: Grid System Operator | I92: 44148 | J92: 20/11/2020 | K92: New
A93: SEB2020L | B93: 0660 | C93: 5CG014DQ2N | E93: HP Elitebook 840 G6 | F93: Adam | G93: Jong Lung Sin | H93: Asset Management | I93: 13/11/2020 | J93: 16/11/2020 | K93: New
A94: SEB2020L | B94: 0659 | C94: 5CG014DSKH | E94: HP Elitebook 840 G6 | F94: CFJ | G94: Kenny Samson Anak Michael | H94: Distribution (Warehouse 1) | I94: 13/11/2020 | J94: 16/11/2020 | K94: Replace Desktop PC
A95: SEB2020L | B95: 0658 | C95: 5CG014DSKL | E95: HP Elitebook 840 G6 | F95: JW | G95: Maslina Bujang | H95: Corporate Admin | I95: 44147 | J95: 44154 | K95: Replace NB | L95: Returned Old Laptop on 20/11/2020
A96: SEB2020L | B96: 0657 | C96: 5CG014DSL5 | E96: HP Elitebook 840 G6 | F96: Art | G96: Shirley Lee Ming Yieng | H96: Distribution | I96: 13/11/2020 | J96: 17/11/2020
A97: SEB2020L | B97: 0656 | C97: 5CG014DQG4 | E97: HP Elitebook 840 G6 | F97: Adam | G97: Siti Husmiyatie Akbar Jahan | H97: Grid System Operator | I97: 13/11/2020 | J97: 20/11/2020 | K97: New
A98: SEB2020L | B98: 0655 | C98: 5CG014DRN9 | E98: HP Elitebook 840 G6 | F98: CFJ | G98: Alistair Yong Jin Hin | H98: Distribution (Warehouse 1) | I98: 44176 | J98: 13/11/2020 | K98: Replace Desktop PC
A99: SEB2020L | B99: 0654 | C99: 5CG014DQN3 | E99: HP Elitebook 840 G6 | F99: AC | G99: Noor Azlinda Bt Abdul Talip | H99: Grid System Management | I99: 27/11/2020 | J99: 44086 | K99: Replacement
A100: SEB2020L | B100: 0653 | C100: 5CG014DT85 | E100: HP Elitebook 840 G6 | F100: Art | G100: YB Encik Gerald Rentap Jabu | H100: SESCO Board | I100: 44176 | J100: 13/11/2020 | K100: New | L100: Returned laptop on 04/10/2024 (Resigned)
...

Sheet Baleh HEP Assigned Computername
A1: Computer Name | C1: S/N | D1: Model | E1: Done by | F1: User Name | G1: Department | H1: Completed | I1: Date of Collection | J1: New / Replacement | K1: Returned Old Laptop / Desktop
A2: BLP2020L | B2: 0001 | C2: 5CG00920X8 | D2: HP Elitebook 840 G6 | E2: Adam | F2: Reuben Anak Jagai
A3: BLP2020L | B3: 0002 | C3: 5CG00920X2 | D3: HP Elitebook 840 G6 | E3: Adam | F3: Iliyana Kazulianie Binti Mansor
A4: BLP2020L | B4: 0003 | D4: HP Elitebook 840 G6
A5: BLP2020L | B5: 0004 | C5: 5CCG00920X9 | D5: HP Elitebook 840 G6 | E5: JW | F5: Dora Jau
A6: BLP2020L | B6: 0005 | C6: 5CG00906WF | D6: HP Elitebook 840 G6 i7 | E6: Art | F6: Kho Kiat Chai | G6: PD | H6: 17/03/2021 | I6: 44291 | J6: Replacement
A7: BLP2020L | B7: 0006 | C7: 5CG00920WW | D7: HP Elitebook 840 G6 | E7: Adam | F7: Paul Michael Raj | G7: PD | I7: 19-may-2021
A8: BLP2020L | B8: 0007 | C8: 5CG00920WV | D8: HP EB840 G6 (i7) | E8: ULH | F8: myvacseb | G8: Baleh HEP | H8: 16/06/2021 | I8: 18/06/2021 | J8: New
A9: BLP2020L | B9: 0008 | C9: 5CG00920X6 | D9: HP EB840 G6 (i7) | E9: ULH | F9: myvacseb | G9: Baleh HEP | H9: 16/06/2021 | I9: 18/06/2021 | J9: New
A10: BLP2020L | B10: 0009 | C10: 5CG00920WZ | D10: HP EB840 G6 (i7) | E10: ULH | F10: myvacseb | G10: Baleh HEP | H10: 16/06/2021 | I10: 18/06/2021 | J10: New
A11: BLP2020L | B11: 0010 | C11: 5CG00906WG | D11: HP EB840 G6 (i7) | E11: ULH | F11: myvacseb | G11: Baleh HEP | H11: 16/06/2021 | I11: 18/06/2021 | J11: New
A12: BLP2020L | B12: 0011 | D12: HP Elitebook 840 G6
A13: BLP2020L | B13: 0012 | D13: HP Elitebook 840 G6
A14: BLP2020L | B14: 0013 | C14: 5CG00906WP | D14: HP Elitebook 840 G6 | E14: Adam | F14: Irene Anak Deli
A15: BLP2020L | B15: 0014 | C15: 5CG00920X1 | D15: HP EB840 G6 (i7) | E15: ULH | F15: Rusydi Bin Raba'ie | G15: Baleh HEP | H15: 44115 | I15: 23/11/2020 | J15: New | K15: BLP2020L0001 change to 14
A16: BLP2020L | B16: 0015 | C16: 5CG00920X3 | D16: HP EB840 G6 (i7) | E16: ULH | F16: Sedah Anak Jagop | G16: Baleh HEP | H16: 23/11/2020 | I16: 43933 | J16: New | K16: BLP2020L0002 change to 15
A17: BLP2020L | B17: 0016 | C17: 5CG00920X0 | D17: HP EB840 G6 (i7) | E17: ULH | F17: Abdul Fazil bin Abdul Manan | G17: Baleh HEP | H17: 23/11/2020 | I17: 43933 | J17: New | K17: BLP2020L0003 change to 16
A18: BLP2020L | B18: 0017 | C18: 5CG00906WK | D18: HP EB840 G6 (i7) | E18: ULH | F18: Daniel anak Abel | G18: Baleh HEP | H18: 23/11/2020 | I18: 43933 | J18: New | K18: BLP2020L0004 change to 17
A19: BLP2020L | B19: 0018 | C19: 5CG00920WS | D19: HP EB840 G6 (i7) | E19: ULH | F19: Timothy Hii Lu Cherng | G19: Baleh HEP | H19: 44348 | I19: 44230 | J19: New | K19: BLP2020L0005 change to 18
A20: BLP2020L | B20: 0019 | C20: 5CG00906WM | D20: HP EB840 G6 (i7) | E20: ULH | F20: Kemmy anak John | G20: Baleh HEP | H20: 24/02/2021 | I20: 44230 | J20: New | K20: BLP2020L0006 change to 19
A21: BLP2020L | B21: 0020 | C21: 5CG00920WR | D21: HP EB840 G6 (i7) | F21: Rumpang Anak Usat@Gumbang | G21: Baleh HEP | K21: Ex-Catherine Encharang
A23: BLP2021L | B23: 0001 | C23: 5CG00920XB | D23: HP EB840 G6 (i7) | E23: ULH | F23: Alex anak Ladi | G23: Baleh HEP | H23: 28/07/2021 | I23: 44538 | J23: New
A24: BLP2021L | B24: 0002 | C24: 5CG00920WP | D24: HP EB840 G6 (i7) | E24: ULH | F24: Nichard anak Nichol | G24: Baleh HEP | H24: 44538 | I24: 44531 | J24: New
A25: BLP2021L | B25: 0003 | C25: 5CG00920XC | D25: HP EB840 G6 (i7) | E25: ULH | F25: Thomas Chin Jun Yen | G25: Baleh HEP | H25: 11/26/2021 | I25: 44529 | J25: New
A26: BLP2021L | B26: 0004 | C26: 5CG00920X7 | D26: HP EB840 G6 (i7) | E26: ULH | F26: Anthony Njok Balan | G26: Baleh HEP | H26: 44705 | I26: 44719 | J26: New
A27: BLP2021L | B27: 0005 | C27: Reserve | D27: HP EB840 G6 (i7) | E27: ULH | G27: Baleh HEP | J27: New
A28: BLP2021L | B28: 0006 | C28: 5CG00920X4 | D28: HP EB840 G6 (i7) | E28: JWPJ | F28: Bong Chien Chai | G28: Baleh HEP | H28: 44419 | I28: 44440 | J28: New | K28: User resigned - Laptop returned on 25/1/2022 | L28: Re-assign to Jonathan.
A29: BLP2021L | B29: 0007 | C29: 5CG00906WH | D29: HP EB840 G6 (i7) | E29: Arth | F29: Jaynsen Anak Patrick Sibat | G29: Baleh HEP | H29: 12-Oct-2021 | J29: New | K29: S11290
A30: BLP2021L | B30: 0008 | C30: 5CG00906WD | D30: HP EB840 G6 (i7) | F30: Lim Chew Hin | G30: Baleh HEP | I30: 03-Jan-2022 | J30: New Joiner | K30: Received @HQ 14-Oct-2021
A31: BLP2021L | B31: 0009 | C31: 5CG00920WT | D31: HP EB840 G6 (i7) | E31: Adam | F31: Nayli Batrisyia Binti Nordin | G31: Baleh HEP | J31: New Joiner | K31: Received @HQ 14-Oct-2021
A32: BLP2021L | B32: 0010 | C32: 5CG00920WY | D32: HP EB840 G6 (i7) | E32: Adam | F32: Alexson Sangau Anak John | G32: Baleh HEP | H32: 44805 | J32: New Joiner | K32: Received @HQ 14-Oct-2021 | L32: OSSM # S20590
A33: BLP2021L | B33: 0011 | C33: 5CG00920WQ | D33: HP EB840 G6 (i7) | E33: Adam | F33: Fatin Syazwin Bt. Sukor | G33: Baleh HEP | J33: New Joiner | K33: Received @HQ 14-Oct-2021 | L33: OSSM # S20656

Sheet NOT BY ICT
B1: Computers that were not purchased by ICT
B2: Joined to Domain with approval
B4: Computer Name | C4: Serial Number | D4: Brand/Model | E4: Username | F4: Location | G4: Dept/Division | H4: Requestor | I4: OSSM Ticket Number
B5: SE2023TCCBTU001 | C5: D37502BH80224 | E5: BINRDC | F5: Bintulu TCC Display Signage | G5: TCC | H5: Desmond Ong/Clashovic | I5: S24301
B6: SE2023TCCBTU002 | C6: D37502BH80665 | E6: BINRDC | F6: Bintulu TCC Display Signage | G6: TCC | H6: Desmond Ong/Clashovic | I6: S24301
B7: SE2023TCCMIR003 | C7: D37502GH10619 | E7: MIRRDC | F7: MINI PC for Miri TCC Display Signage | G7: TCC | H7: Desmond Ong/Chen Foo Yowi | I7: S24264

Sheet Reassigned Laptops_PC
B1: Returned Laptops/Desktop for re-assign
B3: Assign Date | C3: Computer Name | D3: Serial No. | E3: For User | F3: Dept/Div | G3: Requester | H3: OSSM # | I3: Previous User | J3: New requester contract period | K3: C.C. | L3: Completed | M3: Identifier | N3: Recovery Key
C4: SEB10L6846 | D4: 5CG916730F | E4: QKAFFADZEL ZHARFAN BIN KAMAL - | F4: Wayleave Consultant | G4: Muhammad Hanif Bin Morshidi | H4: S13765 | J4: Work contract : 3 Jan 2022 till 2 Jan 2024
C5: SEB01L4809 | D5: 8WK0QN2 | E5: Catherine Pua Mei Ling - | F5: Wayleave Consultant | G5: Muhammad Hanif Bin Morshidi | H5: S13766 | I5: Ex-Goh Lee Hoon | J5: Work contract : 3 Jan 2022 till 2 Jan 2024
C6: SEB10L6898 | D6: 5CG91630G5 | E6: Aiman Bin Alfian - | F6: Wayleave Consultant | G6: Muhammad Hanif Bin Morshidi | H6: S13764 | I6: Ex-Muhammad Nur Khairi | J6: Work contract : 3 Jan 2022 till 2 Jan 2024
C7: SEB2020L0538 | D7: 5CG014DSX8 | E7: ICT Tender SEUser01 | I7: Bunyak Lunyong | J7: Bunyak assigned with HP X360 G7
B9: 44889 | C9: SEB2021L1097 | D9: 5CG1419M7Z | E9: Nurshafeena Binti Zainal Abidin | F9: PDD Consultant, Electrical Engineering | G9: Elysha Anak Woa | H9: S23491 | I9: Ex-Winston Ling | J9: Contract from 03-Jan-2023 - 24 months
B10: 44889 | C10: SEB2022L0815 | D10: 5CG1419M13 | E10: Lucy Saroja Daui Michael Thilleveran | F10: GCEO Office | G10: -- | I10: Ex-Luk Ing Ping | J10: Replace Lucy's Dell 7490 SEB10L5431
B11: 44929 | C11: SEB2020L0752 | D11: 5CG0207MN1 | E11: Liew Swee Chen | F11: Distribution - Maintenance, KRO | G11: -- | H11: S24589 | I11: Ex-Chang Lee Ling
B12: 44929 | C12: SEB2021L0844 | D12: 5CG1032VBS | E12: Mohd Faizal Bin Sarkawi | F12: Distribution - Maintenance, KRO | G12: -- | H12: S24188 | I12: Ex-Alex Lai
B13: 44932 | C13: SEB10D5660 | D13: 4CE9091TZW | E13: Taqiuddin Bin Ahmad Kendong | F13: HSSE - Centre of Excellence | G13: Taqiuddin Bin Ahmad Kendong | H13: S24937 | I13: Ex-Annie Sim Pei Tsu | J13: ACS at Menara Sarawak Energy.
E14: Taqiuddin Bin Ahmad Kendong | F14: HSSE - Centre of Excellence | G14: Taqiuddin Bin Ahmad Kendong | H14: S24946 | J14: ACS at Wisma SESCO.
E15: Taqiuddin Bin Ahmad Kendong | F15: HSSE - Centre of Excellence | G15: Taqiuddin Bin Ahmad Kendong | H15: S24945 | J15: ACS at Kuching Regional Office.
B16: 44936 | C16: SEB2021L0621 | D16: 5CG1036D2J | E16: Valery Lirang Laing - CFS | F16: Project Delivery - Office Support | G16: Nur Yasmin Binti Abdul Halim | H16: S25066 | I16: Ex-Stephanie Chin | J16: 44928 | K16: S25066 | L16: 20-Jan-2023
B17: 44936 | C17: SEB2021L1048 | D17: 5CG1117Q9V | E17: Deckie Anak Lawai - CFS | F17: Project Delivery - Office Support | G17: Nur Yasmin Binti Abdul Halim | H17: S25068 | I17: Ex-Ann-Marie Tan Wei Ping | J17: 44928 | K17: 710123
B18: 44938 | C18: SEB10L5949 | D18: 5CG9167C12 | E18: JULIUS ANAK WILLIAM DEE - CFS | F18: R&D Environmental Sciences | G18: Luk Ing Ping | H18: S25232 | I18: Ex-Huong Yuli | J18: 02-Jan-2023 to 31-Jan-2025 | K18: 510103 | L18: 17-Jan-2023
B19: 44938 | C19: SEB2021L1020 | D19: 5CG1032VQX | E19: Awang Seiful Bahari bin Awang Shawal | F19: Distribution - Warehouse Management | G19: Charles Ak Fidelis Batest | H19: S25219 | I19: Ex- Angelo Emanuel Robin | J19: Awangh Seiful - Shared Dekstop PC user. | K19: 510146
B20: 44938 | C20: SEB2021L0303 | D20: 5CG1036B5B | E20: Chan Kit Hie | F20: Project Delivery - Quality Assurance & Quality Controls | G20: Matthias Michel Peter | H20: S25264 | I20: Jackie Amar | J20: 1-Feb-2023 to 31-Jan-2025 | K20: 710124
B21: 44957 | C21: SEB2021L1089 | D21: 5CG1432GTN | E21: Tan Chuan Ngan | F21: Hydro - Office Support | G21: Ting Li Cheng | H21: S25741 | I21: Tan Chuan Ngan | J21: CFS w.e.f. 01-Feb-2023 | K21: 110105
B22: 44963 | C22: SEB2021L0459 | D22: 5CG1036GRZ | E22: Esther Anak Andrew Mapi | F22: Corporate Services | G22: Esther Anak Andrew Mapi | H22: S25970 | I22: Amanda Lee Hsiao Ling | J22: Re-assigned to Esther. | K22: 510169 | L22: 23-Mar-2023
B23: 44966 | C23: SEB2021L1243 | D23: 5CG1432J47 | E23: Tan Boon Hui | F23: Contract & Procurement - Capital Works | G23: Lim Lee Chin | H23: S26025 | I23: Kho Chung Ho | J23: Re-assigned to Tan Boon Hui | K23: 710122 | L23: 17-Feb-2023
C24: SEB2021L1275 | D24: 5CG1432G45 | I24: Hetty Munira
B25: 44965 | C25: SEB2020L0518 | D25: 5CG014DQ1L | E25: Justine Pengiran ak Igai | F25: ICT | G25: Elizabeth Kueh | H25: S25895 | I25: Tan Cho Yian | J25: CFS w.e.f. 01-Mar-2023 | K25: 610114
B26: 44972 | C26: SEB2021L1504 | D26: CND12345CC | E26: Shitian Ling | F26: Strategy & Corporate Development | G26: -- | I26: Jonny Wong (Bakun) | J26: Replace 5CG9167BQ4 HP 840 G5 | L26: 15-Feb-2023
I27: Naday Kalem
I28: Lily Henry
B29: 44998 | C29: SEB2021L1132 | D29: 5CG1432GTQ | E29: Afi Bazilah Binti Abu | F29: Project Delivery | G29: Nurul Yasmin Binti Abdul Halim | H29: S27405 | I29: Muhammad Saifuddin Bin Bakri | J29: CFS w.e.f 03-April-2023 | K29: 710123 | L29: 23-Mar-2023
B30: 45007 | C30: SEB2021L1374 | D30: 5CG1432GKC | E30: Siti Aishah Binti Abdullah | F30: Project Delivery | G30: Anatasha Anak Johnnes Gobli | H30: S27584 | I30: Mohd Shuffy Bin Suhaidi | J30: CFS w.e.f 01-May-2023 | K30: 710121
C31: SEB2021L1517 | D31: 5CG1432HJO | I31: Dennis Chee Jun Sheng
B32: 45121 | C32: SEB2021L1808 | D32: 5CG1432HGK | E32: Aliff Adafi Bin mahmud | F32: HR | G32: Kimberley Ak Engkamat | H32: S31341 | I32: Yong Hua Keh | J32: Intern w.e.f. 31-July-2023. | K32: 510168
B33: 45121 | C33: SEB2021L1005 | D33: 5CG1032VHN | E33: Andrea Jane Ak Intai | F33: HR | G33: Kimberley Ak Engkamat | H33: S31348 | I33: Hafizam Bin Zamani | J33: Intern w.e.f. 31-July-2023. | K33: 510168
B34: 45152 | C34: SEB2020L0792 | D34: 5CG01472F6 | E34: Jimmy Ling/Gary Royston | F34: Transmission - Electrical Works | G34: Gary Royston | H34: S31127 | I34: Kelvin Jee Yap Yin | J34: For software testing | K34: 210103
C35: SEB10L5877 | D35: 5CG9123MLM | I35: Aveline Wong
C36: SEB10L4338 | D36: 5CG740304P | I36: Robin Kueh Kay Heng
C37: SEB01L6306 | D37: 5CG91673S4 | I37: Arfindy Ak Tajan
B38: 45127 | C38: SEB2023L2512 | D38: 5CG21631Z6 | E38: Chin Soon Ted | F38: HSSE - Occupational Safety | G38: Chin Soon Ted | H38: S31541 | I38: Elizabeth Lim Ya Wen
C39: SEB2022L2333 | D39: 5CG21631BS | E39: Chai Chiaw Wei | F39: CPG | I39: Ong Sie Siong
B40: 45141 | C40: SEB2022L2152 | D40: 5CG21630HG | E40: Willi Anak Miruk | F40: ICT - Data Center Management | G40: Kartina Wong Chin Ping | H40: S31775 | I40: Kenny Kueh Yung Shin
B41: 45166 | C41: SEB06D7270 | D41: 4CE9140KR3 | E41: Anbrey Law Buong Shyuan | F41: ICT - Data Center Management | G41: Anbrey Law Buong Shyuan | H41: S32578 | I41: Dyg Euis Julianti Bt Awang Mustfa | K41: 610108
B42: 45366 | C42: SEB2022L2038 | D42: 5CG216322T | E42: Deborah Anak Amit - CFS | F42: ICT - Infra | G42: Lee Yih Siew | H42: S40510 | I42: Leonora Liong Peh Ling | J42: 1 April 2024 - 31 March 2026 | L42: 15-Mar-2024
B43: 45398 | C43: SEB2021L1119 | D43: 5CG1432GWS | E43: GEC Room Laptop | F43: GCEO Office | G43: Arthanasius Koppier | I43: Lily Kong | L43: 16-Apr-2024
B44: 45405 | C44: SEB2021L0608 | D44: 5CG1036GRY | E44: Nurhaziema Binti Bolhan - CFS | F44: R&D Laboratory Services | G44: Tay Ming Ming | H44: S42046 | I44: Boniface Benjamin | J44: 2 May 2024 - 1 May 2026 | L44: 23-Apr-2024
B45: 45407 | C45: SEB2021L1550 | D45: 5CG1432G3T | E45: Felicia Josephine anak Jefferson | F45: Project Delivery | G45: Khadtijah Binti Kassim | H45: S41683 | I45: Kukuh Karyantoro | J45: Contract End on 31 July 2025 | K45: 710131 | L45: 25-Apr-2024
B46: 45420 | C46: SEB2022L2068 | D46: 5CG21630LT | E46: Prescilla Shudden Anak Jungan | F46: R&D Laboratory Services | G46: Ajoy Anak Delo | H46: S42588 | I46: Fong Oii Kah | J46: 05/06/2024 to 4/6/2026 | K46: 510103 | L46: 04-May-2024
B47: 45432 | C47: SEB2022L2235 | D47: 5CG216306W | E47: Becky Foo Wei Peng | F47: ICT | G47: Becky Foo Wei Peng | H47: S38373 | I47: Alice Liu Pei Nyuk | K47: 610103 | L47: 20-May-2024
B48: 45454 | C48: SEB2022L2260 | D48: 5CG2162ZVM | E48: Tina Lau Kee Kee | F48: Finance | G48: Wong Chin Hung | H48: S43423 | I48: Kelvin Liew Chin Lee | J48: 01/07/2024 to 30/06/2026 | K48: 510123 | L48: 11-Jun-2024
B49: 45471 | C49: SEB2023L3531 | D49: 5CG3220QVZ | E49: Alan Lim Chong Beng | F49: Project Delivery | G49: Prishilla Tony | H49: S42801 | I49: Susan Chin Ai Ling | J49: 01/07/2024 to 30/06/2026 | K49: 710129 | L49: 28-Jun-2024
B50: 45476 | C50: SEB2023L3380 | D50: 5CG3220SLT | E50: Chan Beng Huat | F50: ICT | G50: Kenny Wong Toh Wee | H50: S44304 | I50: Fendra Anak Nigong | J50: 1 July 2024 to 30 June2025 | K50: 610108 | L50: 03-July-2024
B51: 45484 | C51: SEB2021L0823 | D51: 5CG1032VFB | E51: Audrey Chan Kim Lia | F51: Finance | G51: Tiong Mee Ing | H51: S44794 | I51: Ang Meng Soon | J51: 1 August 2024 to 31 July2026 | K51: 510128 | L51: 24-July-2024
B52: 45503 | C52: SEB2023L2854 | D52: 5CG2292JCQ | E52: Veronica Ng Hui Chung | F52: Business Development | G52: Harwinda Binti Hariono | H52: S45082 | I52: Jeffery Anak Bannet Bagor | J52: 1 August 2024 to 31 July2025 | K52: 510107 | L52: 30-July-2024
B53: 45504 | C53: SEB2023L2715 | D53: 5CG2292J7T | E53: Amid Marcus | F53: SEB Power | G53: Joel Pengiran Ejau | H53: S45340 | I53: Wee Peng Feng | J53: 1 August 2024 to 31 July2026 | K53: 8050022 | L53: 31-July-2024
B54: 45519 | C54: SEB2023L3706 | D54: 5CG3220RVZ | E54: Lee Siew Mien | F54: Finance | G54: Ho Jin Chiat | H54: S45202 | I54: Ullia Ulanda anak Rumpang | J54: 2 September 2024 to 1 September 2026 | K54: 510126 | L54: 15-Aug-2024
B55: 45519 | C55: SEB2021L1576 | D55: 5CG1432G36 | E55: Dayangku Nur Iman Binti Awang Abdul Razak | F55: BFI | G55: Gillian Anak Andrew Lissem | H55: S45877 | I55: Serrie Anak Menda | J55: 2 September 2024 to 1 September 2026 | K55: 710109 | L55: 15-Aug-2024
B56: 45526 | C56: SEB2023L2795 | D56: 5CG2292JGP | E56: Joseph Ajang | F56: Project Delivery - Project HSSE | G56: Khadtijah Binti Kassim | H56: S44293 | I56: Lim Chew Hin | K56: 710131 | L56: 21-Aug-2024
B57: 45544 | C57: SEB2021L0388 | D57: 5CG1036F4Y | E57: Abang Nur Sadri Asri Bin Abg Razali | F57: Transmission- Operations | G57: Abang Nur Sadri Asri Bin Abg Razali | H57: S43715 | I57: Latifah Bt Subbli | K57: 210102 | L57: 09-Sep-2024
B58: 45554 | C58: SEB2021L0382 | D58: 5CG1036HDX | E58: Mohammad Danial Ersham Bin Roslan | F58: Corporate Services (Event Management & Protocol) | G58: Umi Azreen Binti Matsen | H58: S47063 | I58: Roslani Salleh | J58: 2 September 2024 to 1 September 2026 | K58: 8050023 | L58: 19-Sep-2024
B59: 45560 | C59: SEB2022L2026 | D59: 5CG21630PH | E59: Bryant Engkabang Anak Dian | F59: HSSE - Occupational Safety | G59: Chong Yu Ling | H59: S46844 | I59: Cindy Sylvia Binti Albert Merican | J59: 1 October 2024 to 30 September 2026 | K59: 610107 | L59: 25-Sep-2024
B60: 45561 | C60: SEB2021L1899 | D60: 5CG1432G11 | E60: Jamal Bin Abdullah@Tedong Anak Gunda | F60: HSSE - Occupational Safety | G60: Kramer Chin | H60: S47442 | I60: Martha Carrmen Anak Marconi | J60: 1 October 2024 to 30 September 2026 | K60: 610107 | L60: 26-Sep-2024
B61: 45573 | C61: SEB2023L2839 | D61: 5CG2292HZZ | E61: Zahirunisa Abd Rahim | F61: R&D Environmental Sciences | G61: Zahirunisa Abd Rahim | H61: S47128 | I61: Abdul Baderi Bin Sahmat | K61: 510103 | L61: 08-Oct-2024
B62: 45588 | C62: SEB2021L1846 | D62: 5CG1432HHV | E62: Mohamad Azriel Bin Azman | F62: Hydro | G62: Chia Fuk Jing | H62: S48224 | I62: Milton Anthony Suen | K62: 2010052 | L62: 23-Oct-2024
B63: 45588 | C63: SEB2023L2734 | D63: 5CG2292JCD | E63: Abel Anak Daniel Teho | F63: HSSE - Occupational Safety | G63: Chong Yu Ling | H63: S48033 | I63: Mohamad Ikrma Bin Bujang | J63: 1 November 2024 to 31 October 2026 | K63: 610107 | L63: 23-Oct-2024
B64: 45595 | C64: SEB2021L1018 | D64: 5CG1032VGF | E64: Jackshaman Anak Ahed | F64: Hydro | G64: Curazon Landon Anak Munan | H64: S48465 | I64: Matilda Ting Mee Yu | J64: 1 November 2024 to 31 October 2026 | K64: 110101 | L64: 30-Oct-2024
B65: 45595 | C65: SEB2021L1275 | D65: 5CG1432G45 | E65: Calvin Belulok Ngang | F65: Hydro | G65: Curazon Landon Anak Munan | H65: S48464 | I65: Hetty Munira Binti Mohd Yusof | J65: 1 November 2024 to 31 October 2026 | K65: 110101 | L65: 30-Oct-2024
B66: 45596 | C66: SEB2021L0053 | D66: 5CG1036B4M | E66: Ima Hanida Binti Mashan | F66: Contract & Procurement - Capital Works | G66: Kelvina Kiu Siu Jen | H66: S48580 | I66: Roland Emang | J66: 1 November 2024 to 31 October 2026 | K66: 710128 | L66: 31-Oct-2024
B67: 45624 | C67: SEB2023L3805 | D67: 5CG3220RW9 | E67: Aaron Lim Yeng Zhang | F67: Generation Central Services | G67: Bernard Liew Yang Yang | H67: S49115 | I67: Rose Emmy Anak Kelbin | J67: 2 December 2024 to 1 December 2026 | K67: 8050012 | L67: 28-Nov-2024
B68: 45637 | C68: SEB2021L1103 | D68: 5CG1419MBS | E68: Thomas Chong Gin How | F68: Finance- Financial Accounting | G68: Liu Sze Wei | H68: S49614 | I68: Christina Lai | J68: 2 January 2025 to 1 January 2027 | K68: 8050041 | L68: 11-Dec-2024
B69: 45644 | C69: SEB2022L2243 | D69: 5CG21630DW | E69: Stella Bong Jia Leh | F69: Finance- Financial Accounting | G69: Dayang Nursyahirah Binti Awang Othmee | H69: S50070 | I69: Lorenzoe Lampazz Anak Christopher Minggu | J69: 2 January 2025 to 1 January 2027 | K69: 8050041 | L69: 18-Dec-2024
B70: 45644 | C70: SEB2023L3724 | D70: 5CG3220S7N | E70: Karen Lim Wan Yee | F70: Contract & Procurement - Capital Works - Transmission Line Projects | G70: Nur Amalina Binti Jaapar | H70: S50084 | I70: Chai Pui Yin | J70: 2 January 2025 to 1 January 2027 | K70: 710122 | L70: 18-Dec-2024
B71: 45659 | C71: SEB2023L3303 | D71: 5CG3220QQK | E71: Erweena Binti Suleiman | F71: Contract & Procurement - Bumiputera Vendor Development | G71: Aizzat Affero Bin Jaraiee | H71: S50455 | I71: Tinah Jerome | J71: 2 January 2025 to 1 January 2027 | K71: 8000104001 | L71: 02-Jan-2025
B72: 45660 | C72: SEB2021L0535 | D72: 5CG1036F4W | E72: Awang Muhammad Nur Azirul Bin Awang Anuar | F72: Retail - Pusa, Sri Aman | G72: Keyna Chung Yi Ling | I72: Jonathan Kho Kai | J72: End on September 2026 | K72: 353001 | L72: 03-Jan-2025 | M72: Remark: Taken by Sumiato on 03/01/2025
B73: 45692 | C73: SEB2021L0006 | D73: 5CG1036B4Z | E73: Lionel Leo Renggie Anak Michael Luncha | F73: Contract & Procurement - Capital Works | G73: Lionel Leo Renggie Anak Michael Luncha | H73: S51531 | I73: Muhammad Nur Aiman Bin Ibrahim | K73: 710122 | L73: 04-Feb-2025

Sheet Test-Replacement
B1: Laptop Replaced | C1: Serial # | D1: Model | E1: Loan | F1: Remarks
A2: NB >> NB | B2: SEB10L7196 | C2: 5CD9450R8H | D2: HP EliteBook x360 1030 G4
A3: DT >> NB | F3: Shared Desktop PC user.
A4: NB >> NB | B4: SEB10L3620 | C4: 6645YB2 | D4: Dell Latitude 3470
A5: DT >> NB | F5: Shared Desktop PC user.
A6: DT >> NB | F6: Shared Desktop PC user.
A7: NB >> NB | B7: SEB10L3092 | C7: CND5247SC7 | D7: HP ProBook 440 G2
A8: NB >> NB | B8: SEB10L5281 | C8: F82YPN2 | D8: Dell Latitude 7490
A9: NB >> NB | B9: SEB10L3749 | C9: 2M15YB2 | D9: Dell Latitude 3470
A10: DT >> NB | F10: Shared computer user.
A11: NB >> NB | B11: SEB10L4714 | C11: JR9RPN2 | D11: Dell Latitude 7490
A12: NB >> NB | B12: SEB10L4848 | C12: 7Q1SPN2 | D12: Dell Latitude 7490
A13: DT >> NB | F13: Shared Desktop PC user.
A14: NB >> NB | B14: SEB10L5064 | C14: PF0VM90T | D14: Lenovo T470
A15: NB >> NB | B15: SEB2020L0381 | C15: 5CG014DSW2 | D15: HP EliteBook 840 G6
A16: NB >> NB | B16: SEB10L4602 | C16: FMGYZM2 | D16: Dell Precision 5520
A17: NB >> NB | B17: SEB10L4876 | C17: 81L0QN2 | D17: Dell Latitude 7490
A18: NB >> NB | B18: SEB10L4653 | C18: 76QCZM2 | D18: Dell Latitude 7480
A19: DT >> NB | F19: Shared Desktop PC user (SPC)
A20: DT >> NB | F20: Shared Desktop PC user previously.
A21: NB >> NB | B21: SEB10L4913 | C21: BXNRPN2 | D21: Dell Latitude 7490
A22: NB >> NB | B22: SEB10L4342 | C22: 5CG740301X | D22: HP EliteBook 840 G4
A23: DT >> NB | B23: SEB00D5708 | C23: 4CE909216B | D23: Desktop PC
A24: DT >> NB | B24: SEB00D5684 | C24: 4CE9092176 | D24: HP EliteDesk 800 G4
A25: NB >> NB | B25: SEB10L4194 | C25: 5CG74030K4 | D25: HP EliteBook 840 G4
A26: NB >> NB
A27: NB >> NB
A28: NB >> NB | B28: SEB10L4840 | C28: JZVRPN2 | D28: Dell Latitude 7490
A29: NB >> NB | B29: SEB10L5206 | C29: CDKQPN2 | D29: Dell Latitude 7490
A30: DT >> DT | B30: SEB10D3561 | C30: SGH634STX7 | D30: HP Z640
A31: DT >> NB
A32: DT >> NB
A33: DT >> NB
A34: NB >> NB | B34: SEB10L5446 | C34: 97JSPN2 | D34: Dell Latitude 7490
A35: NB >> NB | B35: SEB10L4603 | C35: BDGYZM2 | D35: Dell Precision 5520
A36: DT >> DT
A37: DT >> NB
A38: NB >> NB | B38: SEB10L4799 | C38: 76HRPN2 | D38: Dell Latitude 7490
A39: NB >> NB | B39: SEB2021L1555 | C39: 5CG1432FNT | D39: HP EliteBook 840 G7
A40: NB >> NB | B40: SEB10L4847 | C40: 5C1SPN2 | D40: Dell Latitude 7490
A41: NB >> NB | B41: SEB10L5108 | C41: BTGRPN2 | D41: Dell Latitude 7490
A42: NB >> NB | B42: SEB10L4788 | C42: 9ZXZPN2 | D42: Dell Latitude 7490
A43: DT >> NB | B43: SEB06L3471
A44: DT >> NB
A45: DT >> NB
A46: DT >> NB
A47: NB >> NB | B47: SEB10L4873 | C47: 9G2YPN2 | D47: Dell Latitude 7490
A48: NB >> NB | B48: SEB2020L0781 | C48: 5CG014DRN8 | D48: Persistent Blue Screen
A49: NB >> NB | B49: SEB10L4254 | C49: 5CG7402ZZD | D49: HP EliteBook 840 G4
A50: NB >> NB | B50: SEB10L5047 | C50: 7D50QN2 | D50: Dell Latitude 7490
A51: DT >> NB | B51: SEB06D5957 | C51: 4CE914D77N | D51: HP EliteDesk 800 G4
A52: DT >> NB | B52: SEB06D5955 | C52: 4CE9140797 | D52: HP EliteDesk 800 G4
A53: NB >> NB | B53: SEB06L3471
A54: DT >> DT | B54: SEB10D1146 | C54: VCB030083E138217 | D54: Acer S6610G
A55: NB >> NB | B55: SEB10L4672 | C55: 6L3RPN2 | D55: Dell Latitude 7490
A56: NB >> NB | B56: SEB10L5268 | C56: CLZYPN2 | D56: Dell Latitude 7490
A57: NB >> NB | B57: SEB10L5188 | C57: 4XB0QN2 | D57: Dell Latitude 7490
A58: NB >> NB | B58: SEB10L4256 | C58: 5CG7402ZTR | D58: HP EliteBook 840 G4
A59: NB >> NB | B59: SEB01L7061 | C59: 5CG91630JR | D59: HP EliteBook 840 G5
A60: DT >> NB | F60: 4CE9091V9S
A61: NB >> NB | B61: SEB14L4212 | C61: 5CG740309G | D61: HP EliteBook 840 G4
A62: NB >> NB | B62: SEB04L5440 | C62: JX4SPN2 | D62: Dell Latitude 7490
A63: NB >> NB
A64: NB >> NB | B64: SEB02L5381 | D64: Dell Latitude 7490
A65: DT >> NB
A66: DT >> NB | F66: Shared Desktop PC user - SEB02D6800
A67: DT >> NB | F67: Shared Desktop PC user - SEB04D6069
A68: DT >> NB | F68: Shared Desktop PC user - SEB04D6069
A69: NB >> NB
A70: NB >> NB | B70: SEB07L4996 | C70: DBKQPN2 | D70: Dell Latitude 7490
A71: NB >> NB | B71: SEB07L5005 | D71: Dell Latitude 7490
A72: NB >> NB | B72: SEB07L5006 | D72: Dell Latitude 7490
A73: NB >> NB | B73: SEB07L5379 | D73: Dell Latitude 7490
A74: NB >> NB | B74: SEB10L5098 | C74: 4ZISPN2 | D74: Dell Latitude 7490
A75: NB >> NB
A76: NB >> NB | B76: SEB01L5290 | C76: C45ZPN2 | D76: Dell Latitude 7490
A77: NB >> NB | B77: SEB10L6216 | C77: 5CG916740V | D77: HP EliteBook 840 G5
A78: DT >> NB
A79: DT >> NB | B79: SEB00D5692 | D79: Desktop PC
A80: NB >> NB | B80: SEB00L4310 | C80: 5CG7403055 | D80: HP EliteBook 840 G4
A81: NB >> NB | B81: SEB01L4187 | C81: 5CG7402ZT7 | D81: HP EliteBook 840 G4
A82: NB >> NB | B82: SEB10L4314 | C82: 5CG7402ZHD | D82: HP EliteBook 840 G4
A83: NB >> NB | B83: SEB10L4297 | C83: 5CG7403081 | D83: HP EliteBook 840 G4
A84: NB >> NB | B84: SEB10L4113 | C84: 5CG73145BR | D84: HP EliteBook 840 G4
A85: NB >> NB | B85: SEB01L5287 | C85: GLQZPN2 | D85: Dell Latitude 7490
A86: DT >> NB | F86: No computer before, shared computer with 3 users
A87: NB >> NB | B87: SEB2020L0075 | C87: 777MM13 | D87: Dell Latitude 5400
A88: NB >> NB | B88: SEB06L4303 | C88: 5CG74030M2 | D88: HP EliteBook 840 G8
A89: DT >> DT | F89: Replace PC3 at Menara Main Guardhouse
A90: DT >> NB | B90: SEB07D5252 | C90: 9NTZ8R2 | D90: OptiPlex 7060
A91: NB >> NB | B91: ICTLOAN290 | C91: 5CG7074G4G
A92: NB >> NB | B92: SEB00L4690 | C92: 84CZPN2 | D92: Latitude 7490
A93: DT >> NB | B93: SEB2019D0021 | C93: 4CE909216C | D93: HP EliteDesk 800 G4
A94: NB >> NB | B94: SEB01L5286 | C94: D0P0QN2 | D94: Dell Latitude 7490
A95: NB >> NB | B95: SEB10L4298 | C95: 5CG740307P | D95: HP EliteBook 840 G4
A96: NB >> NB | B96: SEB10L3662 | C96: 6K15YB2 | D96: Dell Latitude 3470
A97: NB >> NB | B97: SEB10L5092 | C97: 95P0QN2 | D97: Dell Latitude 7490
A98: NB >> NB | B98: SEB10L5133 | C98: DVNRPN2 | D98: Dell Latitude 7490
A99: NB >> NB | B99: SEB10L4718 | C99: DQNRPN2 | D99: Dell Latitude 7490
A100: DT >> NB | D100: HP EliteDesk
...

Sheet Sheet2
A1: Date | B1: User name
A2: 01-Dec-2021 | B2: Zaidi Minggu
A3: 01-Dec-2021 | B3: Slyvester Chendang Anak Seman
A4: 01-Dec-2021 | B4: Mohamad Yusuf Tan Abdullah
A5: 02-DEC-2021 | B5: Nur Iqmal Bin Khirudin
A6: 06-Dec-2021 | B6: Anne Sabine Ak Pamap
A7: 07-Dec-2021 | B7: Wong Ing Siong
A8: 08-Dec-2021 | B8: George Harrison Lee Anak Joblee
A9: 08-Dec-2021 | B9: Mohamad Khairul Sarini Bin Bujang
A10: 09-Dec-2021 | B10: Peter Alphonso
A11: 09-Dec-2021 | B11: Gabriel Robson Anak Muton
A12: 09-Dec-2021 | B12: Azra Arina binti Zainurin
... A39: 14-Dec-2021 | B39: LIM CHEW HIN
A40: 44501 | B40: NUR AINIZA BINTI ZAKARIA
A41: 44501 | B41: Carlos Fong Vun Poh
A42: 44501 | B42: Marini Bte Merikan
A43: 44501 | B43: Wilson Juan Anak Baie
A44: 44501 | B44: Nelson Ak Mangkau
A45: 44501 | B45: Rimond Ijau Anak Bata
A46: 44501 | B46: Mohammad Salahuddin Bin Abu Bakar
A47: 44501 | B47: Edward Bin Bernabas Semait
A48: 44501 | B48: Lim Shu Lip
A49: 44501 | B49: Navin Iswandi Bin Bujang
A50: 44501 | B50: Yazid Bin Yakup
A51: 44503 | B51: Husni Diyana Binti Sarbini
... A101: 44530 | B101: Aimi Binti Zainuddin
B103: Dennis Harun ?
A105: CFS
A106: 44516 | B106: Cindy Sylvia Binti Albert Merican
A107: 44516 | B107: Thomas Chin Jun Yen
A108: 30-09-2021 | B108: Mohd. Endi Joni
A109: 04-Oct-2021 | B109: Abdul Mannaff bin Alias
A110: 05-Oct-2021 | B110: Lorderizk Nawang Simon
A111: 05-Oct-2021 | B111: JESSICA EMPANG LIAN
A112: 05-Oct-2021 | B112: Anne Eliza Anak Dolim
A113: 05-Oct-2021 | B113: DELLA ANAK RAMBA
A114: 05-Oct-2021 | B114: Albert Chew Kwang Heng
A115: 05-Oct-2021 | B115: Lee Tian Sang
A116: 05-Oct-2021 | B116: Benard Chen
A117: 07-Oct-2021 | B117: Danesh Mailvaganam
A118: 11-Oct-2021 | B118: Nurin Afiqah Binti Senu
A119: 11-Oct-2021 | B119: Gouvinraj a/l Lechmanan Palanisamy
... A152: 27-Oct-2021 | B152: Muhamad Amierul Iqmal Mohamad Tahir
A155: OTHERS
A156: 26-Oct-2021 | B156: Hassanuddin Bin Abdul Rahman
A157: 18-Oct-2021 | B157: Ariffin Narwes Bin Muhammad Juhin
A158: 14-Oct-2021 | B158: Nadzilla Zalikha Binti Noh
A159: 14-Oct-2021 | B159: Nathaniel Reviellee Lau
A160: 01-10-2021 | B160: Cary CASSON Ripin
A165: TRAINEES
A166: 04-Oct-2021 | B166: Mirza Faizi Shahmir Bin Faizal Ashikin
A167: 04-Oct-2021 | B167: Nur Batrisyia Affrizah Binti Apian
A168: 04-Oct-2021 | B168: Gibson Panyau Anak Jackson Rodi
A169: 07-Oct-2021 | B169: Syed Muhamad Haziq Bin Wan Habib Othman
A170: 11-Oct-2021 | B170: Azzahreena bt Juraimi
A171: 12-Oct-2021 | B171: Delton Sako Anak Derald Kuwang
A177: SECURITY - REQUEST FOR LAPTOP
A178: 07-Oct-2021 | B178: Kenneth Majing Anak Ujal
A179: 20-Oct-2021 | B179: Bob Rissy Anak Buor
A180: 44440 | B180: Dato Ir. Abang Jemat Bin Abang Bujang
A181: 44440 | B181: Datu Haji Wan Kassim Bin Tuanku Zubir
A182: 44440 | B182: Dr. Simon Sinang Anak Bada
A183: 44440 | B183: Ir. Cr. Haji Zawawi Bin Haji Embong
A184: 44440 | B184: Stell Anak Sindau
A185: 44440 | B185: Dzulkornain bin Masron
A186: 44440 | B186: Datu Haji Abang Halmi Bin Tan Sri Ikhwan
A187: 44440 | B187: Dato Allan Keripin Nangkai
A188: 44440 | B188: Datuk Mutang Tagal
A189: 44441 | B189: Yong Li Ping
A190: 44433 | B190: Philip Alung
A191: 44441 | B191: Jefina Anak Jeffrey James
... A222: 44468 | B222: Nathaniel Elisha Chin Ak Ngelambong
A223: 30/9/21 | B223: Wong Yew Yiin
A224: 30/9/21 | B224: Lembang Anak Iba
A225: 30/9/21 | B225: Khoo Hui Kiang
A226: 30/9/21 | B226: MICHAEL BENGGANG MARTIN
A227: 30/9/21 | B227: Jaynsen Anak Patrick Sibat
A228: 30/9/21 | B228: Kathy Prescilla Anak Jeludin
A231: SECURITY
A232: 44454 | B232: Mohamad Yusuf Tan Abdullah
A235: SEPT LOAN
A236: 44445 | B236: Ryan anak Gaybrist
A237: 44445 | B237: Mohd Khairul Hakimie Bin Abu Bakar Sidek
A238: 44456 | B238: Nuraina Najihah Bt Affendi
A239: 44462 | B239: Nur Batrisyeea Binti Kamaludin
A241: 44467 | B241: Ridhwan Zharif Bin Nasya
A242: 44410 | B242: Tan Kok Fan
A243: 44411 | B243: Andi Sipi
A244: 44411 | B244: Mohamad Khairul Mek Abdullah
A245: 44412 | B245: Mohamad Ezzy Aizuddyn B Mahmud
A246: 44412 | B246: Matha Gamau
A247: 44412 | B247: Michelle Binti Aparid @ Alfred
A248: 44412 | B248: Zainal Abidin Bin Ahmad
... A280: 44427 | B280: Boniface Benjamin
A281: 5CG1419MC6 | B281: Arthur Ambau Anak Boniface
A282: 44431 | B282: Jong Chee Kee
A283: 44431 | B283: Qarmizi Sofyan Bin Hamli
A284: 44433 | B284: Stephanie Chin Pei Yii
A285: 44453 | B285: Nurul Hamizah Binti Hiduat @ Daan
A286: 44433 | B286: Abdul Muin Bin Mustafa
...

Sheet 2021 NEW
A1: Computer Name | C1: S/N | D1: Encryption | E1: Model | F1: Assign To | G1: User Name | H1: Department | I1: S | J1: Section/Division | L1: Completed | M1: Date Laptop Assigned | N1: New/Adhoc/Replace | O1: Month Requested | P1: Ticket No. | Q1: Remarks | R1: Identifier | S1: Recovery Key
A2: SEB2021L | B2: 0001 | C2: 5CG1036DRR | D2: y | E2: HP EliteBook 840 G7 | F2: Aziz | G2: Mohd. Zulhazis Bin Brahim | H2: Distribution | J2: Dalat | K2: Sibu | L2: 19/04/2021 | M2: 21/04/2021 | O2: =_xlfn.XLOOKUP(G2,Sheet2!B:B,Sheet2!A:A,"",0,1) | P2: Reserved for vendor servcies
A3: SEB2021L | B3: 0002 | C3: 5CG1036C1K | D3: Y | E3: HP EliteBook 840 G7 | F3: Yip | G3: Julian Ak Peter | H3: Retail | K3: Wisma | L3: 31-Mar-2021 | M3: 31-Mar-2021 | N3: DT >> NB | O3: =_xlfn.XLOOKUP(G3,Sheet2!B:B,Sheet2!A:A,"",0,1) | P3: "
A4: SEB2021L | B4: 0003 | C4: 5CG1036DCY | D4: Bitlocker | E4: HP EliteBook 840 G7 | F4: MHZ | G4: Stephenie Alvina Dadi | H4: Distribution | J4: Operational Excellence | K4: Bintulu | L4: 44443 | M4: 44443 | N4: DT >> NB | O4: =_xlfn.XLOOKUP(G4,Sheet2!B:B,Sheet2!A:A,"",0,1) -> 44271 | P4: " | R4: 36011E62-BC25-448C-8153-2DE22CAEF61A | S4: 344267-622006-060654-581955-334928-070840-557645-338261
A5: SEB2021L | B5: 0004 | C5: 5CG1036F5B | D5: Y | E5: HP EliteBook 840 G7 | F5: Yip | G5: Kho Li Fang | H5: Retail | K5: Wisma | L5: 31-Mar-2021 | M5: 31-Mar2021 | N5: DT >> NB | O5: =_xlfn.XLOOKUP(G5,Sheet2!B:B,Sheet2!A:A,"",0,1) | P5: "
A6: SEB2021L | B6: 0005 | C6: 5CG1032VFG | E6: HP EliteBook 840 G7 | F6: AC | G6: Eunice Chai Yuan Shiun | K6: Menara | L6: 19-Mar-2021 | M6: 17-May-2021 | N6: New Request | O6: =_xlfn.XLOOKUP(G6,Sheet2!B:B,Sheet2!A:A,"",0,1) -> 44270 | P6: " | R6: DT >> DT
A7: SEB2021L | B7: 0006 | C7: 5CG1036B4Z | D7: Bitlocker | E7: HP EliteBook 840 G7 | F7: Art | G7: Muhammad Nur Aiman Bin Ibrahim Lionel Leo Renggie Anak Michael Luncha | H7: PDD Contract & Procurement - Capital Works | I7: 710122 | J7: Contract & Procurement - Capital Works | K7: Sibu | L7: 6-Apr-2021 | M7: 20-Apr-2021 | O7: =_xlfn.XLOOKUP(G7,Sheet2!B:B,Sheet2!A:A,"",0,1) | P7: S51531 | R7: DT >> NB
A8: SEB2021L | B8: 0007 | C8: 5CG1036GF7 | D8: y | E8: HP EliteBook 840 G7 | F8: AC | G8: Ulok Kalang | H8: SPC | K8: SPC | L8: 29-Mar-2021 | M8: 06-Apr-2021 | N8: NB >> NB | O8: =_xlfn.XLOOKUP(G8,Sheet2!B:B,Sheet2!A:A,"",0,1) -> 44270 | P8: " | R8: NB >> NB
A9: SEB2021L | B9: 0008 | C9: 5CG1036F4L | E9: HP EliteBook 840 G7 | G9: Muhammad Tarmizi Bin Abdul Hamid | H9: SEB Power | K9: Menara | M9: 17-Aug-2021 | O9: =_xlfn.XLOOKUP(G9,Sheet2!B:B,Sheet2!A:A,"",0,1) -> 44272 | P9: " | R9: New Joiner
A10: SEB2021L | B10: 0009 | C10: 5CG1036C1J | D10: y | E10: HP EliteBook 840 G7 | F10: Aziz | G10: Yap Kuok Chiang | H10: Mukah - Petian | K10: Mukah | L10: 19/04/2021 | M10: 21/04/2021 | O10: =_xlfn.XLOOKUP(G10,Sheet2!B:B,Sheet2!A:A,"",0,1) | P10: " | R10: New Request
A11: SEB2021L | B11: 0010 | C11: 5CG1036D3B | D11: y | E11: HP EliteBook 840 G7 | F11: Aziz | G11: Affendy Bin Nawi | H11: Distribution | K11: Dalat | L11: 19/04/2021 | M11: 21/04/2021 | O11: =_xlfn.XLOOKUP(G11,Sheet2!B:B,Sheet2!A:A,"",0,1) | P11: "
A12: SEB2021L | B12: 0011 | C12: 5CG1036HDY | D12: Bitlocker | E12: HP EliteBook 840 G7 | F12: MHZ | G12: Amirah Binti Zaidel | J12: Operational Excellence | K12: Bintulu | L12: 44443 | M12: 44443 | N12: DT >> NB | O12: =_xlfn.XLOOKUP(G12,Sheet2!B:B,Sheet2!A:A,"",0,1) -> 44271 | P12: " | R12: DB27C95D-323C-4D23-A80C-61CA740465AA | S12: 698346-601117-009240-528946-498531-237490-688083-461967
A13: SEB2021L | B13: 0012 | C13: 5CG1036GFP | D13: y | E13: HP EliteBook 840 G7 | F13: Aziz | G13: Mohamad Jamalludin Bin Arsat | H13: Mukah - Petian | K13: Mukah | L13: 20/04/2021 | M13: 22/04/2021 | O13: =_xlfn.XLOOKUP(G13,Sheet2!B:B,Sheet2!A:A,"",0,1) | P13: "
A14: SEB2021L | B14: 0013 | C14: 5CG1036BV1 | D14: Y | E14: HP EliteBook 840 G7 | F14: MHZ | G14: Boon Koh Zack | H14: Store - Bintulu Power Station | K14: Bintulu | L14: 16/04/2021 | M14: 16/04/2021 | O14: =_xlfn.XLOOKUP(G14,Sheet2!B:B,Sheet2!A:A,"",0,1) | P14: " | R14: Kuching
A15: SEB2021L | B15: 0014 | C15: 5CG1036BV2 | D15: Y | E15: HP EliteBook 840 G7 | F15: MHZ | G15: Clayvian Anak Joshua | H15: Store - Bintulu Power Station | K15: Bintulu | L15: 16/04/2021 | M15: 16/04/2021 | O15: =_xlfn.XLOOKUP(G15,Sheet2!B:B,Sheet2!A:A,"",0,1) | P15: " | R15: Sibu
A16: SEB2021L | B16: 0015 | C16: 5CG1036GF4 | D16: Bitlocker | E16: HP EliteBook 840 G7 | F16: MHZ | G16: Victor Nyagang Wong King Kai | H16: Mechanical - Bintulu Power Station | K16: Bintulu | L16: 16/04/2021 | M16: 16/04/2021 | N16: DT >> NB | O16: =_xlfn.XLOOKUP(G16,Sheet2!B:B,Sheet2!A:A,"",0,1) | P16: " | R16: Miri | T16: 6FFE9611-4767-47C7-A421-0A62E961FA35 (Identifier)
A17: SEB2021L | B17: 0016 | C17: 5CG1036C8Z | D17: Bitlocker | E17: HP EliteBook 840 G7 | F17: Fairul | G17: Molis Alissong Anak Noyeng | H17: RMD | K17: Wisma SESCO | L17: 20-Apr-2021 | M17: 22-Apr-2021 | N17: NB >> NB | O17: =_xlfn.XLOOKUP(G17,Sheet2!B:B,Sheet2!A:A,"",0,1) -> 44272 | P17: S3673 | R17: Sri Aman
A18: SEB2021L | B18: 0017 | C18: 5CG1036GRD | D18: y | E18: HP EliteBook 840 G7 | F18: Aziz | G18: Norman Bin James Spawi | H18: Distribution | K18: Dalat | M18: 21/04/2021 | O18: =_xlfn.XLOOKUP(G18,Sheet2!B:B,Sheet2!A:A,"",0,1) -> 44274 | P18: " | R18: Sarikei
A19: SEB2021L | B19: 0018 | C19: 5CG1036F4H | E19: HP EliteBook 840 G7 | F19: Adam | G19: Marissa Binti Edwin Yassin Abdullah | H19: Contract Procurement & Governance | K19: Kuching | L19: 29-Mar-2021 | M19: 01-April-2021 | O19: =_xlfn.XLOOKUP(G19,Sheet2!B:B,Sheet2!A:A,"",0,1) -> 44271 | P19: " | R19: Bintulu
A20: SEB2021L | B20: 0019 | C20: 5CG1036DST | D20: Y | E20: HP EliteBook 840 G7 | F20: Aziz | G20: Norhalek Bin Mohd Syaifol @ Atek | H20: Mukah - Petian | K20: Mukah | L20: 19/04/2021 | M20: 22/04/2021 | O20: =_xlfn.XLOOKUP(G20,Sheet2!B:B,Sheet2!A:A,"",0,1) | P20: "
A21: SEB2021L | B21: 0020 | C21: 5CG1036DRT | D21: Bitlocker | E21: HP EliteBook 840 G7 | F21: ULH | G21: Jenifer Jakub | H21: Distribution | K21: Sibu | L21: 19/04/2021 | M21: 21/04/2021 | O21: =_xlfn.XLOOKUP(G21,Sheet2!B:B,Sheet2!A:A,"",0,1) -> 44273 | P21: " | R21: 2D5EEDD8-D4CD-4AAB-8572-04BE40E8E6FC | S21: 247236-072490-098868-100529-495363-487201-626945-169994
A22: SEB2021L | B22: 0021 | C22: 5CG1036B4W | D22: Bitlocker | E22: HP EliteBook 840 G7 | F22: JW | G22: Yong Jin Cheok | H22: Transmission | K22: Menara | L22: 29/03/2021 | M22: 44347 | N22: NB >> NB | O22: =_xlfn.XLOOKUP(G22,Sheet2!B:B,Sheet2!A:A,"",0,1) | P22: " | R22: 96785E28-0F0B-4F9A-872D-BEFB19CB17EE | S22: 543235-301136-327833-216513-086944-432542-128524-135960
A23: SEB2021L | B23: 0022 | C23: 5CG1036GFC | D23: Y | E23: HP EliteBook 840 G7 | F23: AC | G23: Charles Gregory Anak Kipo | H23: Transmission | K23: Menara | L23: 29-Mar-2021 | M23: 03-May-2021 | N23: NB >> NB | O23: =_xlfn.XLOOKUP(G23,Sheet2!B:B,Sheet2!A:A,"",0,1) | P23: "
A24: SEB2021L | B24: 0023 | C24: 5CG1036GZ8 | D24: Bitlocker | E24: HP EliteBook 840 G7 | F24: JW | G24: Mohamad Tajuddin Bin Mohd Nazir | H24: Transmission | K24: Menara | L24: 29/03/2021 | M24: 44351 | N24: NB >> NB | O24: =_xlfn.XLOOKUP(G24,Sheet2!B:B,Sheet2!A:A,"",0,1) | P24: " | R24: E81A49CA-73DF-4083-BE8E-D5C2DF102809 | S24: 410784-044946-381403-330121-708719-406329-446754-174119
A25: SEB2021L | B25: 0024 | C25: 5CG1036C1H | D25: Bitlocker | E25: HP EliteBook 840 G7 | F25: JW | G25: Chupak Ak Insam | H25: Security | K25: Menara | L25: 29/03/2021 | M25: 44319 | N25: DT >> NB | O25: =_xlfn.XLOOKUP(G25,Sheet2!B:B,Sheet2!A:A,"",0,1) | P25: " | R25: FA2F220A-B69D-461D-8EB5-8F58ADDBC308 | S25: 016126-708092-158235-089727-489500-710281-182204-360745
A26: SEB2021L | B26: 0025 | C26: 5CG1036H4L | D26: Y | E26: HP EliteBook 840 G7 | F26: ULH | G26: Osman Bin Bujang Japar | H26: Distribution | K26: CR | L26: 44443 | M26: 44534 | O26: =_xlfn.XLOOKUP(G26,Sheet2!B:B,Sheet2!A:A,"",0,1) -> 44272 | P26: "
A27: SEB2021L | B27: 0026 | C27: 5CG1036BTP | D27: Bitlocker | E27: HP EliteBook 840 G7 | F27: Jacob | G27: BERA SIM | H27: BAKUN | K27: BAKUN | L27: 29/04/2021 | M27: 44291 | O27: =_xlfn.XLOOKUP(G27,Sheet2!B:B,Sheet2!A:A,"",0,1) -> 44273 | P27: " | R27: B925C4CF-1406-4C42-8E3C-8CCEE024DDEE | S27: 401203-541783-686609-056716-160380-509333-575245-639331
A28: SEB2021L | B28: 0027 | C28: 5CG1036BTT | D28: Bitlocker | E28: HP EliteBook 840 G7 | F28: Aziz | G28: Sandu Anak Julai | H28: GIS | K28: Sibu | L28: 21/04/2021 | M28: 21/04/2021 | N28: DT >> NB | O28: =_xlfn.XLOOKUP(G28,Sheet2!B:B,Sheet2!A:A,"",0,1) -> 44272 | P28: " | R28: 700889BA-8902-4601-92C6-2985361B820F | S28: 616209-352033-001815-093632-242583-527175-568953-037939
A29: SEB2021L | B29: 0028 | C29: 5CG1036GG3 | D29: Y | E29: HP EliteBook 840 G7 | F29: Jacob | G29: Moniliza Mujan Merang | H29: BAKUN | K29: Murum | L29: 29/04/2021 | M29: 04-May-2021 | O29: =_xlfn.XLOOKUP(G29,Sheet2!B:B,Sheet2!A:A,"",0,1) -> 44273 | P29: "
A30: SEB2021L | B30: 0029 | C30: 5CG1036GG0 | D30: y | E30: HP EliteBook 840 G7 | F30: Jacob | G30: JANE ERING | H30: BAKUN | K30: Murum | L30: 29/04/2021 | M30: 04-May-2021 | O30: =_xlfn.XLOOKUP(G30,Sheet2!B:B,Sheet2!A:A,"",0,1) -> 44273 | P30: "
A31: SEB2021L | B31: 0030 | C31: 5CG1036DDS | D31: Bitlocker | E31: HP EliteBook 840 G7 | F31: Yip | G31: CHUA SIEW YUN | K31: Kuching | L31: 24/03/2021 | M31: 26-March-2021 | N31: NB >> NB | P31: " | R31: F0913883-5B8A-47A5-BCE6-52D6626CDFF7 | S31: 283778-220781-497739-225709-251625-231693-600468-584958
A32: SEB2021L | B32: 0031 | C32: 5CG1036F4J | D32: Y | E32: HP EliteBook 840 G7 | F32: Aziz | G32: Pau Siu Yew | H32: Retail | K32: Sibu | L32: 15/04/2021 | M32: 17-Aug-2021 | N32: DT >> NB | O32: =_xlfn.XLOOKUP(G32,Sheet2!B:B,Sheet2!A:A,"",0,1) | P32: "
A33: SEB2021L | B33: 0032 | C33: 5CG1036DRX | D33: Bitlocker | E33: HP EliteBook 840 G7 | F33: ULH | G33: Tracy Anak Henry Mundu | H33: Distribution | K33: Sibu | L33: 21/04/2021 | M33: 21/04/2021 | N33: DT >> NB | O33: =_xlfn.XLOOKUP(G33,Sheet2!B:B,Sheet2!A:A,"",0,1) -> 44273 | P33: " | R33: 01E3C137-678A-4818-A2DF-E60525C51C29 | S33: 686983-462924-517462-510213-313203-712426-074129-238799
A34: SEB2021L | B34: 0033 | C34: 5CG1036DRP | D34: Bitlocker | E34: HP EliteBook 840 G7 | F34: Art | G34: Harold Anak Muhi | H34: Wayleave | K34: Menara | L34: 7-Apr-2021 | M34: 19-Apr-2021 | N34: DT >> NB | P34: "
A35: SEB2021L | B35: 0034 | C35: 5CG1036F43 | E35: HP EliteBook 840 G7 | F35: Adam | G35: Evelintina Edora Anak Sedempet | H35: Wayleave | K35: Menara | L35: 29-Mar-2021 | M35: 31-Mar-2021 | O35: =_xlfn.XLOOKUP(G35,Sheet2!B:B,Sheet2!A:A,"",0,1) | P35: "
A36: SEB2021L | B36: 0035 | C36: 5CG1036C9M | E36: HP EliteBook 840 G7 | G36: Terrence Blawan Ak Nuhip@Nyoging | K36: Menara | M36: 06-Sept-2021 | O36: =_xlfn.XLOOKUP(G36,Sheet2!B:B,Sheet2!A:A,"",0,1) | P36: "
A37: SEB2021L | B37: 0036 | C37: 5CG1036F49 | D37: Bitlocker | E37: HP EliteBook 840 G7 | G37: Anthony Leo Anak Akitson | K37: Menara | M37: 06-Sept-2021 | O37: =_xlfn.XLOOKUP(G37,Sheet2!B:B,Sheet2!A:A,"",0,1) | P37: " | R37: 59B1EB31-7F07-4BCE-A2C2-5828A35292AF | S37: 424545-235972-056870-029733-551056-627231-381601-174746
A38: SEB2021L | B38: 0037 | C38: 5CG1036C1G | E38: HP EliteBook 840 G7 | G38: Caleen Anak James Parot | K38: Menara | M38: 17-Aug-2021 | O38: =_xlfn.XLOOKUP(G38,Sheet2!B:B,Sheet2!A:A,"",0,1) | P38: "
A39: SEB2021L | B39: 0038 | C39: 5CG1036F4F | D39: Bitlocker | E39: HP EliteBook 840 G7 | F39: Art | G39: Quinnsay Anak Patrick | H39: Wayleave | K39: Menara | L39: 8-Apr-2021 | M39: 20-Apr-2021 | N39: DT >> NB | P39: "
A40: SEB2021L | B40: 0039 | C40: 5CG1036DSM | E40: HP EliteBook 840 G7 | F40: Yip | G40: Sabrina Rafaella | H40: Retail | K40: Wisma | L40: 25-Mar-2021 | M40: 25-Mar-2021 | O40: =_xlfn.XLOOKUP(G40,Sheet2!B:B,Sheet2!A:A,"",0,1) | P40: "
A41: SEB2021L | B41: 0040 | C41: 5CG1036D3C | E41: HP EliteBook 840 G7 | G41: Gregory Daud Rubin | H41: RES | K41: Kuching | M41: 17-Aug-2021 | O41: =_xlfn.XLOOKUP(G41,Sheet2!B:B,Sheet2!A:A,"",0,1) -> 44272 | P41: "
A42: SEB2021L | B42: 0041 | C42: 5CG1036GGF | E42: HP EliteBook 840 G7 | F42: WSM | G42: Romeo Heng | H42: Project | K42: Sarikei | M42: 01-April 2021 | O42: =_xlfn.XLOOKUP(G42,Sheet2!B:B,Sheet2!A:A,"",0,1) -> * | P42: "
A43: SEB2021L | B43: 0042 | C43: 5CG1036F41 | E43: HP EliteBook 840 G7 | F43: WSM | G43: Suziliana Binti Subeli | H43: Project | K43: Sarikei | M43: 01-April 2021 | O43: =_xlfn.XLOOKUP(G43,Sheet2!B:B,Sheet2!A:A,"",0,1) -> * | P43: "
A44: SEB2021L | B44: 0043 | C44: 5CG1036C1Z | E44: HP EliteBook 840 G7 | F44: WSM | G44: Rachel Anak Amit | H44: Project | K44: Sarikei | M44: 01-April 2021 | O44: =_xlfn.XLOOKUP(G44,Sheet2!B:B,Sheet2!A:A,"",0,1) -> * | P44: "
A45: SEB2021L | B45: 0044 | C45: 5CG1036CWF | D45: Y | E45: HP EliteBook 840 G7 | F45: ULH | G45: Dayang Nurhasyimah Bt Awang Taib | H45: GIS | K45: Sibu | L45: 29/04/2021 | M45: 29/04/2021 | N45: DT >> NB | O45: =_xlfn.XLOOKUP(G45,Sheet2!B:B,Sheet2!A:A,"",0,1) | P45: "
A46: SEB2021L | B46: 0045 | C46: 5CG1036GRS | E46: HP EliteBook 840 G7 | F46: WSM | G46: Nur Azura Binti Mustafa | H46: Personnel Section | K46: Sarikei | M46: 21-Sept-2021 | O46: =_xlfn.XLOOKUP(G46,Sheet2!B:B,Sheet2!A:A,"",0,1) -> * | P46: (Collected in April 2021)
A47: SEB2021L | B47: 0046 | C47: 5CG1036D2N | E47: HP EliteBook 840 G7 | F47: WSM | G47: Noorhayati Binti Hamid | H47: Disconnection | K47: Sarikei | M47: 01-April 2021 | O47: =_xlfn.XLOOKUP(G47,Sheet2!B:B,Sheet2!A:A,"",0,1) -> * | P47: "
A48: SEB2021L | B48: 0047 | C48: 5CG1036DFD | E48: HP EliteBook 840 G7 | F48: WSM | G48: Leong Li Nah | H48: Retail | K48: Sarikei | M48: 01-April 2021 | O48: =_xlfn.XLOOKUP(G48,Sheet2!B:B,Sheet2!A:A,"",0,1) -> * | P48: "
A49: SEB2021L | B49: 0048 | C49: 5CG1036GG4 | E49: HP EliteBook 840 G7 | F49: WSM | G49: Dzul Fikry Bin Kipli Aizuddin Bin Yusuf | H49: Project | K49: Sarikei | M49: 17-Aug-2021 | O49: =_xlfn.XLOOKUP(G49,Sheet2!B:B,Sheet2!A:A,"",0,1) | P49: " | Q49: Dzul
A50: SEB2021L | B50: 0049 | C50: 5CG1036GF9 | E50: HP EliteBook 840 G7 | F50: WSM | G50: Awang Rosalan Bin Awang Osman | H50: Retail | K50: Sarikei | M50: 05-April-2021 | O50: =_xlfn.XLOOKUP(G50,Sheet2!B:B,Sheet2!A:A,"",0,1) -> * | P50: "
A51: SEB2021L | B51: 0050 | C51: 5CG1032VB2 | D51: Y | E51: HP EliteBook 840 G7 | F51: ULH | G51: Arthur Anak Moner | H51: RES | J51: Sibujaya | K51: Sibu | L51: 13/04/2021 | M51: 13/04/2021 | O51: =_xlfn.XLOOKUP(G51,Sheet2!B:B,Sheet2!A:A,"",0,1) | P51: "
A52: SEB2021L | B52: 0051 | C52: 5CG1036F4N | D52: Bitlocker | E52: HP EliteBook 840 G7 | F52: Yip | G52: Lizanawati Binti Sukiman | H52: Finance | J52: Information & Administration | K52: Menara | M52: 21/04/2021 | O52: =_xlfn.XLOOKUP(G52,Sheet2!B:B,Sheet2!A:A,"",0,1) | P52: " | R52: 82F214C2-DAC4-4705-AFB8-30D9EEA0D5CA | S52: 503833-358919-328966-364045-176473-059576-673552-144265
A53: SEB2021L | B53: 0052 | C53: 5CG1036DDM | D53: Y | E53: HP EliteBook 840 G7 | F53: Aziz | G53: Alexander Fabian Mijen | H53: Mukah - Petian | K53: Mukah | L53: 20/04/2021 | M53: 22/04/2021 | O53: =_xlfn.XLOOKUP(G53,Sheet2!B:B,Sheet2!A:A,"",0,1) -> 44281 | P53: "
A54: SEB2021L | B54: 0053 | C54: 5CG1036B4M | D54: Bitlocker | E54: HP EliteBook 840 G7 | F54: Art | G54: Roland Emang Ima Hanida Binti Mashan | H54: Asset Management Contract & Procurement - Capital Works | J54: Hydro Projects | K54: Menara | L54: 31-Mar-2021 | M54: 44287 | N54: DT >> NB | O54: =_xlfn.XLOOKUP(G54,Sheet2!B:B,Sheet2!A:A,"",0,1) | P54: " | Q54: Reassigned to Ima Hanida Binti Mashan/ ticket S48580
A55: SEB2021L | B55: 0054 | C55: 5CG1036BVJ | D55: Bitlocker | E55: HP EliteBook 840 G7 | F55: JW | G55: Alexander Gotte | K55: Menara | L55: 30/03/2021 | M55: 44287 | N55: NB >> NB | O55: =_xlfn.XLOOKUP(G55,Sheet2!B:B,Sheet2!A:A,"",0,1) | P55: " | R55: 3EFE9DF1-36AF-42EE-B41C-93DF3BCEDEEF | S55: 061512-211761-067760-008239-608498-285197-643929-206844
A56: SEB2021L | B56: 0055 | C56: 5CG1036DSQ | D56: Y | E56: HP EliteBook 840 G7 | F56: AC | G56: Adi Wahid B Mohd Ridzuan | H56: Smart Grid Asset management | K56: Menara | L56: 31-Mar-2021 | M56: 01-Apr-2021 | O56: =_xlfn.XLOOKUP(G56,Sheet2!B:B,Sheet2!A:A,"",0,1) | P56: "
A57: SEB2021L | B57: 0056 | C57: 5CG1036B4V | D57: Y | E57: HP EliteBook 840 G7 | F57: AC | G57: Erma Zuashmiza Bt Rosli | H57: Distribution | J57: Operational Excellence | K57: Menara | L57: 31-Mar-2021 | M57: 31-Mar-2021 | N57: NB >> NB | O57: =_xlfn.XLOOKUP(G57,Sheet2!B:B,Sheet2!A:A,"",0,1) | P57: "
A58: SEB2021L | B58: 0057 | C58: 5CG1036DS8 | E58: HP EliteBook 840 G7 | F58: CHEN | G58: Shaun Fredly Edward Akong | H58: Inventory Management | K58: WR | L58: 44294 | M58: 44300 | N58: New Request | O58: =_xlfn.XLOOKUP(G58,Sheet2!B:B,Sheet2!A:A,"",0,1) | P58: "
A59: SEB2021L | B59: 0058 | C59: 5CG1036DT4 | E59: HP EliteBook 840 G7 | F59: CHEN | G59: Calvin Garai Hansoo | H59: Inventory Management | K59: WR | L59: 44294 | M59: 44300 | N59: New Request | O59: =_xlfn.XLOOKUP(G59,Sheet2!B:B,Sheet2!A:A,"",0,1) -> 44284 | P59: "
A60: SEB2021L | B60: 0059 | C60: 5CG1036BTR | D60: Y | E60: HP EliteBook 840 G7 | F60: MHZ | G60: Mohd Azizi Azzizam B Wahab | H60: Hydro | K60: Murum | L60: 44443 | M60: 44443 | N60: NB >> NB | O60: =_xlfn.XLOOKUP(G60,Sheet2!B:B,Sheet2!A:A,"",0,1) | P60: "
A61: SEB2021L | B61: 0060 | C61: 5CG1036H09 | D61: Bitlocker | E61: HP EliteBook 840 G7 | F61: Yip | G61: Kenneth Ho Chin Ho | H61: Retail | K61: Wisma | M61: 17-Aug-2021 | N61: DT >> NB | O61: =_xlfn.XLOOKUP(G61,Sheet2!B:B,Sheet2!A:A,"",0,1) | P61: " | R61: AE800421-59B3-4C07-A1BE-6E01994050B0 | S61: 612722-262669-420838-405119-716441-496375-494494-507166
A62: SEB2021L | B62: 0061 | C62: 5CG1036C8X | D62: Bitlocker | E62: HP EliteBook 840 G7 | F62: Aziz | G62: Guba Bin Umat | H62: Security | K62: Sibu | L62: 29/04/2021 | M62: 29/04/2021 | N62: NB >> NB | O62: =_xlfn.XLOOKUP(G62,Sheet2!B:B,Sheet2!A:A,"",0,1) -> 44306 | P62: " | R62: 8524BEF7-CC2C-4DF5-B54A-CCAFA22F4B35 | S62: 008536-320397-670637-258599-447700-194414-570669-419903
A63: SEB2021L | B63: 0062 | C63: 5CG1036DDZ | D63: Bitlocker | E63: HP EliteBook 840 G7 | F63: Adam | G63: Dzul Hadzry Bin Husaini | H63: Corporate Services | K63: Menara | L63: 01-April 2021 | M63: 29-April 2021 | O63: =_xlfn.XLOOKUP(G63,Sheet2!B:B,Sheet2!A:A,"",0,1) -> 44282 | P63: " | R63: 96A96C15-1DB6-4699-9486-D822EA3938FA | S63: 106579-321398-102388-311982-523534-491755-143286-068552
A64: SEB2021L | B64: 0063 | C64: 5CG1036F57 | D64: Bitlocker | E64: HP EliteBook 840 G7 | F64: Art | G64: Neillion Anak Samuel Richard Liah | H64: SEB Power | K64: Menara | L64: 1-Apr-2021 | M64: 44293 | N64: DT >> NB | O64: =_xlfn.XLOOKUP(G64,Sheet2!B:B,Sheet2!A:A,"",0,1) | P64: "
A65: SEB2021L | B65: 0064 | C65: 5CG1036BT7 | D65: Bitlocker | E65: HP EliteBook 840 G7 | F65: Yip | G65: Ahmad Faizul Bin Masri | H65: Retail | J65: SCORE Biling | K65: Wisma | L65: 5-Apr-2021 | M65: 13-Apr-2021 | N65: DT >> NB | O65: =_xlfn.XLOOKUP(G65,Sheet2!B:B,Sheet2!A:A,"",0,1) | P65: " | R65: 2EF841FE-FC79-48ED-83C1-5DBE9B120D61 | S65: 615670-348832-133441-708763-625086-679118-189332-272910
A66: SEB2021L | B66: 0065 | C66: 5CG1036BT2 | E66: HP EliteBook 840 G7 | F66: WSM | G66: Eric Roy Ak James Bakir | H66: Distribution | J66: P&P | K66: Western | M66: 21-April-2021 | O66: =_xlfn.XLOOKUP(G66,Sheet2!B:B,Sheet2!A:A,"",0,1) | P66: "
A67: SEB2021L | B67: 0066 | C67: 5CG1036D3G | E67: HP EliteBook 840 G7 | F67: WSM | G67: Stanley Kam Ak Bajat | H67: Project | K67: Sarikei | M67: 22-April-2021 | O67: =_xlfn.XLOOKUP(G67,Sheet2!B:B,Sheet2!A:A,"",0,1) | P67: "
A68: SEB2021L | B68: 0067 | C68: 5CG1036CW1 | E68: HP EliteBook 840 G7 | F68: WSM | G68: Casper Danggat anak Ima | K68: Sarikei | M68: 21-April-2021 | O68: =_xlfn.XLOOKUP(G68,Sheet2!B:B,Sheet2!A:A,"",0,1) -> 44287 | P68: "
A69: SEB2021L | B69: 0068 | C69: 5CG1036BV6 | E69: HP EliteBook 840 G7 | F69: WSM | G69: Vincent Ling Hua Soon | H69: Project | K69: Sarikei | M69: 21-April-2021 | O69: =_xlfn.XLOOKUP(G69,Sheet2!B:B,Sheet2!A:A,"",0,1) -> 44287 | P69: "
A70: SEB2021L | B70: 0069 | C70: 5CG1036H4W | E70: HP EliteBook 840 G7 | F70: WSM | G70: Ying Chung Huo | H70: Project | K70: Sarikei | M70: 13-April-2021 | O70: =_xlfn.XLOOKUP(G70,Sheet2!B:B,Sheet2!A:A,"",0,1) -> 44287 | P70: "
A71: SEB2021L | B71: 0070 | C71: 5CG1036GZX | E71: HP EliteBook 840 G7 | F71: WSM | G71: Awangku Alfiani Shukery | H71: Distribution | J71: Maintenance | K71: Sarikei | M71: 13-April-2021 | O71: =_xlfn.XLOOKUP(G71,Sheet2!B:B,Sheet2!A:A,"",0,1) | P71: "
A72: SEB2021L | B72: 0071 | C72: 5CG1036DF5 | D72: Bitlocker | E72: HP EliteBook 840 G7 | F72: Art | G72: Nur Shakini Bt Sa'aep | H72: ICT | K72: Menara | L72: 19-Apr-2021 | M72: 19-Apr-2021 | N72: NB >> NB | O72: =_xlfn.XLOOKUP(G72,Sheet2!B:B,Sheet2!A:A,"",0,1) | P72: "
A73: SEB2021L | B73: 0072 | C73: 5CG1036GZK | E73: HP EliteBook 840 G7 | F73: Adam | G73: Lim Sze Ching | K73: Menara | L73: 16-Apr-2021 | M73: 20-Apr-2021 | O73: =_xlfn.XLOOKUP(G73,Sheet2!B:B,Sheet2!A:A,"",0,1) -> 44287 | P73: "
A74: SEB2021L | B74: 0073 | C74: 5CG1036GYW | E74: HP EliteBook 840 G7 | F74: YCY | G74: Mahathir Bin Mohammed | K74: BPG | M74: 30-april-2021 | O74: =_xlfn.XLOOKUP(G74,Sheet2!B:B,Sheet2!A:A,"",0,1) | P74: "
A75: SEB2021L | B75: 0074 | C75: 5CG1036CB9 | D75: Bitlocker | E75: HP EliteBook 840 G7 | G75: Agnes Moi Sylvester | K75: Sibu | M75: 17-Aug-2021 | O75: =_xlfn.XLOOKUP(G75,Sheet2!B:B,Sheet2!A:A,"",0,1) | P75: " | R75: 38409235-EB6C-4AAB-A5B4-E4E414A15C15 | S75: 151921-058960-016203-201817-081455-224345-354024-055165
A76: SEB2021L | B76: 0075 | C76: 5CG1036H03 | E76: HP EliteBook 840 G7 | G76: Dzul Fikry Bin Kipli | H76: Project | K76: Sarikei | M76: 03-April-2021 | O76: =_xlfn.XLOOKUP(G76,Sheet2!B:B,Sheet2!A:A,"",0,1) -> * | P76: "
A77: SEB2021L | B77: 0076 | C77: 5CG1036DSN | D77: Bitlocker | E77: HP EliteBook 840 G7 | F77: Art | G77: Ikhmal Haiqal Ting Abdullah | H77: SPC | K77: SPC | L77: 20-Apr-2021 | M77: 22-Apr-2021 | O77: =_xlfn.XLOOKUP(G77,Sheet2!B:B,Sheet2!A:A,"",0,1) -> 44294 | P77: "
A78: SEB2021L | B78: 0077 | C78: 5CG1036GFZ | E78: HP EliteBook 840 G7 | F78: Aziz | G78: Ting Ho Young | H78: Retail | K78: Sibu | L78: 44352 | M78: 44352 | O78: =_xlfn.XLOOKUP(G78,Sheet2!B:B,Sheet2!A:A,"",0,1) -> 44287 | P78: "
A79: SEB2021L | B79: 0078 | C79: 5CG1036DDT | D79: Bitlocker | E79: HP EliteBook 840 G7 | F79: JW | G79: Tan Wan Soo | K79: Menara | L79: 44357 | M79: 28-June-2021 | O79: =_xlfn.XLOOKUP(G79,Sheet2!B:B,Sheet2!A:A,"",0,1) | P79: "
A80: SEB2021L | B80: 0079 | C80: 5CG1036F5J | E80: HP EliteBook 840 G7 | F80: Adam | G80: Mcfarlane Chua Kang Wei | K80: Menara | L80: 13-Apr-2021 | M80: 22-Apr-2021 | N80: NB >> NB | O80: =_xlfn.XLOOKUP(G80,Sheet2!B:B,Sheet2!A:A,"",0,1) | P80: "
A81: SEB2021L | B81: 0080 | C81: 5CG1036C1L | D81: Bitlocker | E81: HP EliteBook 840 G7 | F81: MHZ | G81: Josie Eda Ak Cyril | H81: Retail | K81: Bintulu | L81: 23/04/2021 | M81: 23/04/2021 | O81: =_xlfn.XLOOKUP(G81,Sheet2!B:B,Sheet2!A:A,"",0,1) | P81: "
A82: SEB2021L | B82: 0081 | C82: 5CG1036F4X | E82: HP EliteBook 840 G7 | F82: Adam | G82: Caesar Ak Raymond | H82: Wayleave | K82: Menara | L82: 19-Apr-2021 | M82: 22-Apr-2021 | O82: =_xlfn.XLOOKUP(G82,Sheet2!B:B,Sheet2!A:A,"",0,1) | P82: "
A83: SEB2021L | B83: 0082 | C83: 5CG1036D3F | E83: HP EliteBook 840 G7 | F83: JW | G83: James Ak Nase | H83: Wayleave | K83: Menara | L83: 19/4/2021 | M83: 44308 | N83: NB >> NB | O83: =_xlfn.XLOOKUP(G83,Sheet2!B:B,Sheet2!A:A,"",0,1) | P83: "
A84: SEB2021L | B84: 0083 | C84: 5CG1036C9V | D84: Bitlocker | E84: HP EliteBook 840 G7 | F84: lew | G84: Wong Leng Huong | H84: Distribution | K84: Sibu | L84: 44505 | M84: 17-Aug-2021 | N84: DT >> NB | O84: =_xlfn.XLOOKUP(G84,Sheet2!B:B,Sheet2!A:A,"",0,1) | P84: OSSM S6192 | R84: 81F53303-E09D-4DFB-A011-8F2B2BA17093 | S84: 394581-499862-069157-606342-259061-454850-140668-318153
A85: SEB2021L | B85: 0084 | C85: 5CG1036CVT | E85: HP EliteBook 840 G7 | G85: Pheron Anak Titus Raymond Jayim | H85: Transmission | K85: Kuching | L85: 44370 | M85: 28-June-2021 | O85: =_xlfn.XLOOKUP(G85,Sheet2!B:B,Sheet2!A:A,"",0,1) | P85: "
A86: SEB2021L | B86: 0085 | C86: 5CG1036C1X | D86: Y | E86: HP EliteBook 840 G7 | F86: Aziz | G86: Mohamad Haindera Bin Sapian | H86: Distribution | K86: Sibu | L86: 29/5/2021 | M86: 44261 | O86: =_xlfn.XLOOKUP(G86,Sheet2!B:B,Sheet2!A:A,"",0,1) -> 44291 | P86: "
A87: SEB2021L | B87: 0086 | C87: 5CG1036CWP | D87: Bitlocker | E87: HP EliteBook 840 G7 | F87: Art | G87: Siti Hamida Bt Abd Hamid Ho | H87: Coal | K87: SPC | L87: 21-Apr-2021 | M87: 26-Apr-2021 | N87: NB >> NB | O87: =_xlfn.XLOOKUP(G87,Sheet2!B:B,Sheet2!A:A,"",0,1) | P87: "
A88: SEB2021L | B88: 0087 | C88: 5CG1036BTS | E88: HP EliteBook 840 G7 | F88: CHEN | G88: Shaunraj Naidu A/L Navaraja Naidu | H88: WR - Kota Samarahan | K88: Kuching | L88: 19/04/2021 | M88: 19/04/2021 | N88: New Request | O88: =_xlfn.XLOOKUP(G88,Sheet2!B:B,Sheet2!A:A,"",0,1) | P88: OSSM # S4714
A89: SEB2021L | B89: 0088 | C89: 5CG1036C8T | E89: HP EliteBook 840 G7 | F89: CHEN | G89: Chin Swee Seng | H89: Distribution | J89: Planning/Project | K89: Kuching | L89: 15/04/2021 | M89: 15/04/2021 | N89: NB >> NB | O89: =_xlfn.XLOOKUP(G89,Sheet2!B:B,Sheet2!A:A,"",0,1) -> 44298 | P89: "
A90: SEB2021L | B90: 0089 | C90: 5CG1036C9N | E90: HP EliteBook 840 G7 | F90: Adam | G90: Muhd Hasbullah Bin Hj Hussen | H90: Retail | K90: Kuching | L90: 16-April 2021 | M90: 22-April 2021 | O90: =_xlfn.XLOOKUP(G90,Sheet2!B:B,Sheet2!A:A,"",0,1) | P90: "
A91: SEB2021L | B91: 0090 | C91: 5CG1036GF2 | D91: Y | E91: HP EliteBook 840 G7 | F91: MHZ | G91: Ha How Chuong | H91: Bintulu Power Station | K91: Bintulu PS | L91: 16/04/2021 | M91: 16/04/2021 | N91: DT >> NB | O91: =_xlfn.XLOOKUP(G91,Sheet2!B:B,Sheet2!A:A,"",0,1) -> 44298 | P91: "
A92: SEB2021L | B92: 0091 | C92: 5CG1036C14 | D92: Bitlocker | E92: HP EliteBook 840 G7 | F92: CHEN | H92: PDD | J92: Engineering Management | K92: Kuching | L92: 44292 | M92: 44361 | N92: NB >> NB | O92: =_xlfn.XLOOKUP(G92,Sheet2!B:B,Sheet2!A:A,"",0,1) -> 0 | P92: " | Q92: Laptop returned 1/10/21 ( Resigned )
A93: SEB2021L | B93: 0092 | C93: 5CG1036CB8 | E93: HP EliteBook 840 G7 | F93: CHEN | G93: Richard Ak Martin Noel | H93: WR - Serian | K93: WR | L93: 21/04/2021 | M93: 21/04/2021 | N93: NB >> NB | O93: =_xlfn.XLOOKUP(G93,Sheet2!B:B,Sheet2!A:A,"",0,1) -> 44298 | P93: "
A94: SEB2021L | B94: 0093 | C94: 5CG1036B4H | E94: HP EliteBook 840 G7 | F94: CHEN | G94: Ike Mcclare Duwas Anak Albert | H94: WR - Serian | K94: WR | L94: 21/04/2021 | M94: 21/04/2021 | N94: NB >> NB | O94: =_xlfn.XLOOKUP(G94,Sheet2!B:B,Sheet2!A:A,"",0,1) -> 44298 | P94: "
A95: SEB2021L | B95: 0094 | C95: 5CG1036C1T | E95: HP EliteBook 840 G7 | F95: CHEN | G95: Muhammad Nazrulrizan Bin Rasidin | H95: WR - Serian | K95: WR | L95: 21/04/2021 | M95: 21/04/2021 | N95: NB >> NB | O95: =_xlfn.XLOOKUP(G95,Sheet2!B:B,Sheet2!A:A,"",0,1) | P95: "
A96: SEB2021L | B96: 0095 | C96: 5CG1036HF5 | E96: HP EliteBook 840 G7 | F96: CHEN | G96: Cosmos Saging | H96: WR - Serian | K96: WR | L96: 21/04/2021 | M96: 21/04/2021 | N96: NB >> NB | O96: =_xlfn.XLOOKUP(G96,Sheet2!B:B,Sheet2!A:A,"",0,1) | P96: "
A97: SEB2021L | B97: 0096 | C97: 5CG1036BR9 | E97: HP EliteBook 840 G7 | F97: CHEN | G97: Herry Ak Dumon | H97: WR - Serian | K97: WR | L97: 26/04/2021 | M97: 20/05/2021 | N97: NB >> NB | O97: =_xlfn.XLOOKUP(G97,Sheet2!B:B,Sheet2!A:A,"",0,1) -> 44299 | P97: "
A98: SEB2021L | B98: 0097 | C98: 5CG1036DFG | E98: HP EliteBook 840 G7 | F98: CHEN | G98: Abg. Morshidi B. Abg. Mansor | H98: Kota Samarahan | K98: WR | L98: 19/04/2021 | M98: 19/04/2021 | N98: NB >> NB | O98: =_xlfn.XLOOKUP(G98,Sheet2!B:B,Sheet2!A:A,"",0,1) -> 44298 | P98: "
A99: SEB2021L | B99: 0098 | C99: 5CG1036D22 | E99: HP EliteBook 840 G7 | F99: BASB | G99: Dennis Anak Sang | H99: WR - Serian | K99: WR | L99: 26/04/2021 | M99: 44474 | N99: DT >> NB | O99: =_xlfn.XLOOKUP(G99,Sheet2!B:B,Sheet2!A:A,"",0,1) | P99: "
A100: SEB2021L | B100: 0099 | C100: 5CG1036CWD | D100: Bitlocker | E100: HP EliteBook 840 G7 | F100: Fairul | G100: Matthias Randy Anak Delaney | H100: Meter | K100: Wisma SESCO | L100: 5-May-2021 | M100: 5-June-2021 | O100: =_xlfn.XLOOKUP(G100,Sheet2!B:B,Sheet2!A:A,"",0,1) | P100: "
...
